Workbook

Sheet Instructions
B2: Marine Fish Marketing Survey - Data Entry Workbook
B3: MS-499 term paper - marketing system of commercially important marine fish species, Chattogram region. Fill only YELLOW cells; BLUE columns calculate themselves; GREY cells are prefilled codes.
B5: 1. Sheet map
B6: Progress_Dashboard | C6: Collected vs target counts per market and actor class - updates by itself, never type here.
B7: Data_Collection_Log | C7: One row per field visit: date, market, collector, session, reference-day flag, interviews done.
B8: Unit_Converter | C8: Type a maund value and read kilograms (and the reverse) using 1 maund = 37.32 kg.
B9: Codebook_Species / Codebook_Markets | C9: Official codes S01-S10 and M1-M6. Use codes everywhere; keep these sheets unchanged.
B10: Form_A_Aratdar / Form_B_Bepari_Faria / Form_R_Khuchra | C10: Trader questionnaires - one respondent per row, IDs already assigned (M1-A-01 ... M6-C-06).
B11: Form_C_Consumer | C11: Exit-intercept consumer slips - one respondent per row.
B12: Price_Observations | C12: CORE dataset: one row per respondent x species quote (buy and sell price, quantity). This sheet feeds the R analysis.
B13: Consumer_Purchases_Focal / Consumer_Other_Fish | C13: Form C species grid and 'any other fish bought' answers, long format.
B14: Form_M_Market_Observation | C14: One row per market - the 12-item infrastructure checklist with evidence source.
B15: Tag_Price_Sheet | C15: Optional displayed-price log (appendix only, not used in hypothesis tests).
B16: QC_Check | C16: Automatic quality flags: duplicates, % sums, missing units, PairID linkage. Review after every entry session.
B18: 2. Price-cell flags (all price columns)
B19: Number (e.g. 850) | C19: BDT price under today's fresh, ice-touched, whole-fish condition.
B20: K | C20: Respondent did not handle this species today.
B21: D | C21: Respondent declined to disclose the price.
B22: 0 and '-' | C22: 0 = true zero (rare); '-' = not applicable. Never leave a species cell empty.
B24: 3. Units, IDs and percentages
B25: Units | C25: Enter the price exactly as quoted (Raw) and pick the unit. Traders usually quote per MAUND (1 maund = 37.32 kg), consumers per KG. The BLUE BDT_per_kg columns convert automatically - do not type in them.
B26: Respondent_ID | C26: Prefilled: {Market}-{Actor}-{Serial}, e.g. M1-A-01, M2-B-05, M3-R-12, M4-C-03. Actor codes: A = aratdar, B = bepari/faria, R = khuchra retailer, C = consumer.
B27: Pair_ID | C27: When a buyer and the matching seller are BOTH interviewed, write the same Pair_ID (e.g. PAIR-001) on both rows. Used for the Wilcoxon signed-rank consistency check.
B28: Percent columns | C28: Enter plain numbers 0-100 (70 means 70%). Cash + MFS + Credit should sum to 100 - QC_Check flags mismatches.
B30: 4. Example entries (illustrations only - do not paste)
B31: Form_A row: | C31: M1-A-01 | M1 | 05/03/2026 | age 46 | Secondary | 18 yrs business | 12 Maund/day | family 6 | rent: Pay, 48000 Yearly | commission: 2.5 Percent | waste 500 Monthly | 6 workers x 700 BDT | storage 2500 Yearly | payment 85 / 10 / 5 | MFS: Regular | problems: ice price, toll, unsold loss
B32: Price_Observations rows: | C32: PO-0001 | M1-A-01 | M1 | Aratdar | S01 | buy 32000 Maund, sell 33500 Maund -> auto 857.45 / 897.64 BDT/kg | qty 8 Maund PO-0002 | M3-R-04 | M3 | Retailer | S06 | buy 240 Kg, sell K (no sale today) | qty 15 Kg
B34: Version 2026-08 | Built for the Methodology V4 instrument battery (Forms A, B, R, M, C + optional tag-price sheet).
B36: সংস্করণ ২ (আপডেট) — ফর্ম-নির্ভুল পরিবর্তন
C37: Form_A: বিদ্যুৎ বিল (Electricity_bill_BDT) ও যন্ত্রাংশ/কুল রক্ষণাবেক্ষণ (Equipment_Cooler_Maintenance_BDT) কলাম সঠিক নামে ঠিক করা হয়েছে।
C38: Form_B: দৈনিক হ্যান্ডেল (কেজি/দিন) কলাম যোগ হয়েছে (আগে বাদ ছিল); লোডিং+আনলোডিং খরচ একটি কলামে মেশানো হয়েছে; পরিবহন ভাড়া এখন "প্রতি ট্রিপ" ভিত্তিতে + ট্রিপের হার (প্রতি কত দিনে কয় ট্রিপ); Transport_mode কলাম বাদ দেওয়া হয়েছে (মূল ফর্মে নেই)।
C39: Form_R: দোকান ভাড়া/বরফ/ধোয়া-পানি খরচ এখন প্রতি-দিন (BDT/day) ভিত্তিতে, আগে ভুলবশত মাসিক ছিল।
C40: Form_C: পেমেন্ট মেথড ও বাজার-পছন্দের কারণের অপশন তালিকা মূল ফর্মের সাথে হুবহু মেলানো হয়েছে (নগদ/বিকাশ/নগদ-অ্যাপ/বাকি; দাম/বৈচিত্র্য/নৈকট্য/বিশুদ্ধতা/পরিচিত দোকান)।
C41: Consumer_Purchases_Focal ও Price_Observations: বিক্রেতা/actor তালিকা মূল ফর্মের ভাষার সাথে মেলানো হয়েছে (খুচরা/ফেরিওয়ালা; Khuchra)।
C42: Progress_Dashboard ও QC_Check-এর সূত্র নতুন কলাম-অবস্থান অনুযায়ী আপডেট করা হয়েছে — কিছু হাতে ঠিক করার দরকার নেই।

Sheet Progress_Dashboard
B2: Field Progress Dashboard - target 120 respondents across 6 markets
B3: Counts update automatically from the Interview_Date column of each form sheet. Never type in this sheet.
B5: Market | C5: Aratdar (5) | D5: Bepari/Faria (5) | E5: Retailer (5) | F5: Consumer (5) | G5: Market total (20) | H5: Form M done
B6: M1 | C6: =COUNTIFS(Form_A_Aratdar!$C$5:$C$40,$B6,Form_A_Aratdar!$D$5:$D$40,"<>") -> 0 | D6: =COUNTIFS(Form_B_Bepari_Faria!$C$5:$C$40,$B6,Form_B_Bepari_Faria!$D$5:$D$40,"<>") -> 0 | E6: =COUNTIFS(Form_R_Khuchra!$C$5:$C$40,$B6,Form_R_Khuchra!$D$5:$D$40,"<>") -> 0 | F6: =COUNTIFS(Form_C_Consumer!$C$5:$C$40,$B6,Form_C_Consumer!$D$5:$D$40,"<>") -> 0 | G6: =SUM(C6:F6) -> 0 | H6: =IF(COUNTIFS(Form_M_Market_Observation!$B$5:$B$10,$B6,Form_M_Market_Observation!$D$5:$D$10,"<>")>0,"Yes","No") -> No
B7: M2 | C7: =COUNTIFS(Form_A_Aratdar!$C$5:$C$40,$B7,Form_A_Aratdar!$D$5:$D$40,"<>") -> 0 | D7: =COUNTIFS(Form_B_Bepari_Faria!$C$5:$C$40,$B7,Form_B_Bepari_Faria!$D$5:$D$40,"<>") -> 0 | E7: =COUNTIFS(Form_R_Khuchra!$C$5:$C$40,$B7,Form_R_Khuchra!$D$5:$D$40,"<>") -> 0 | F7: =COUNTIFS(Form_C_Consumer!$C$5:$C$40,$B7,Form_C_Consumer!$D$5:$D$40,"<>") -> 0 | G7: =SUM(C7:F7) -> 0 | H7: =IF(COUNTIFS(Form_M_Market_Observation!$B$5:$B$10,$B7,Form_M_Market_Observation!$D$5:$D$10,"<>")>0,"Yes","No") -> No
B8: M3 | C8: =COUNTIFS(Form_A_Aratdar!$C$5:$C$40,$B8,Form_A_Aratdar!$D$5:$D$40,"<>") -> 0 | D8: =COUNTIFS(Form_B_Bepari_Faria!$C$5:$C$40,$B8,Form_B_Bepari_Faria!$D$5:$D$40,"<>") -> 0 | E8: =COUNTIFS(Form_R_Khuchra!$C$5:$C$40,$B8,Form_R_Khuchra!$D$5:$D$40,"<>") -> 0 | F8: =COUNTIFS(Form_C_Consumer!$C$5:$C$40,$B8,Form_C_Consumer!$D$5:$D$40,"<>") -> 0 | G8: =SUM(C8:F8) -> 0 | H8: =IF(COUNTIFS(Form_M_Market_Observation!$B$5:$B$10,$B8,Form_M_Market_Observation!$D$5:$D$10,"<>")>0,"Yes","No") -> No
B9: M4 | C9: =COUNTIFS(Form_A_Aratdar!$C$5:$C$40,$B9,Form_A_Aratdar!$D$5:$D$40,"<>") -> 0 | D9: =COUNTIFS(Form_B_Bepari_Faria!$C$5:$C$40,$B9,Form_B_Bepari_Faria!$D$5:$D$40,"<>") -> 0 | E9: =COUNTIFS(Form_R_Khuchra!$C$5:$C$40,$B9,Form_R_Khuchra!$D$5:$D$40,"<>") -> 0 | F9: =COUNTIFS(Form_C_Consumer!$C$5:$C$40,$B9,Form_C_Consumer!$D$5:$D$40,"<>") -> 0 | G9: =SUM(C9:F9) -> 0 | H9: =IF(COUNTIFS(Form_M_Market_Observation!$B$5:$B$10,$B9,Form_M_Market_Observation!$D$5:$D$10,"<>")>0,"Yes","No") -> No
B10: M5 | C10: =COUNTIFS(Form_A_Aratdar!$C$5:$C$40,$B10,Form_A_Aratdar!$D$5:$D$40,"<>") -> 0 | D10: =COUNTIFS(Form_B_Bepari_Faria!$C$5:$C$40,$B10,Form_B_Bepari_Faria!$D$5:$D$40,"<>") -> 0 | E10: =COUNTIFS(Form_R_Khuchra!$C$5:$C$40,$B10,Form_R_Khuchra!$D$5:$D$40,"<>") -> 0 | F10: =COUNTIFS(Form_C_Consumer!$C$5:$C$40,$B10,Form_C_Consumer!$D$5:$D$40,"<>") -> 0 | G10: =SUM(C10:F10) -> 0 | H10: =IF(COUNTIFS(Form_M_Market_Observation!$B$5:$B$10,$B10,Form_M_Market_Observation!$D$5:$D$10,"<>")>0,"Yes","No") -> No
B11: M6 | C11: =COUNTIFS(Form_A_Aratdar!$C$5:$C$40,$B11,Form_A_Aratdar!$D$5:$D$40,"<>") -> 0 | D11: =COUNTIFS(Form_B_Bepari_Faria!$C$5:$C$40,$B11,Form_B_Bepari_Faria!$D$5:$D$40,"<>") -> 0 | E11: =COUNTIFS(Form_R_Khuchra!$C$5:$C$40,$B11,Form_R_Khuchra!$D$5:$D$40,"<>") -> 0 | F11: =COUNTIFS(Form_C_Consumer!$C$5:$C$40,$B11,Form_C_Consumer!$D$5:$D$40,"<>") -> 0 | G11: =SUM(C11:F11) -> 0 | H11: =IF(COUNTIFS(Form_M_Market_Observation!$B$5:$B$10,$B11,Form_M_Market_Observation!$D$5:$D$10,"<>")>0,"Yes","No") -> No
B12: TOTAL | C12: =SUM(C6:C11) -> 0 | D12: =SUM(D6:D11) -> 0 | E12: =SUM(E6:E11) -> 0 | F12: =SUM(F6:F11) -> 0 | G12: =SUM(G6:G11) -> 0 | H12: =IF(G12=120,"TARGET MET","In progress") -> In progress
B14: Dataset progress
B15: Interviews entered (of 120) | C15: =G12 -> 0
B16: Target reached (%) | C16: =G12/120 -> 0
B17: Price_Observations rows entered | C17: =COUNTIF(Price_Observations!$C$5:$C$504,"<>") -> 0
B18: of which Aratdar quotes | C18: =COUNTIF(Price_Observations!$E$5:$E$504,"Aratdar") -> 0
B19: of which Bepari/Faria quotes | C19: =COUNTIF(Price_Observations!$E$5:$E$504,"Bepari_Faria") -> 0
B20: of which Retailer quotes | C20: =COUNTIF(Price_Observations!$E$5:$E$504,"Khuchra") -> 0
B21: Consumer_Purchases_Focal rows entered | C21: =COUNTIF(Consumer_Purchases_Focal!$B$5:$B$354,"<>") -> 0
B22: Consumer_Other_Fish rows entered | C22: =COUNTIF(Consumer_Other_Fish!$B$5:$B$104,"<>") -> 0
B23: Tag_Price_Sheet rows entered (optional) | C23: =COUNTIF(Tag_Price_Sheet!$C$5:$C$324,"<>") -> 0
B24: Data_Collection_Log days used | C24: =COUNTIF(Data_Collection_Log!$B$5:$B$44,"<>") -> 0
B26: Quota per market: 5 aratdar + 5 bepari/faria + 5 khuchra retailers + 5 consumers (Methodology Table 3.3).

Sheet Data_Collection_Log
B2: Data Collection Log - one row per field visit
B4: Date | C4: Weekday | D4: Market | E4: Collector_name | F4: Session_start | G4: Session_end | H4: Ref_day_prices_used | I4: Traders_interviewed | J4: Consumers_interviewed | K4: Weather_notes | L4: Notes
C5: =IF($B5="","",TEXT($B5,"ddd"))
C6: =IF($B6="","",TEXT($B6,"ddd"))
C7: =IF($B7="","",TEXT($B7,"ddd"))
C8: =IF($B8="","",TEXT($B8,"ddd"))
C9: =IF($B9="","",TEXT($B9,"ddd"))
C10: =IF($B10="","",TEXT($B10,"ddd"))
C11: =IF($B11="","",TEXT($B11,"ddd"))
C12: =IF($B12="","",TEXT($B12,"ddd"))
C13: =IF($B13="","",TEXT($B13,"ddd"))
C14: =IF($B14="","",TEXT($B14,"ddd"))
C15: =IF($B15="","",TEXT($B15,"ddd"))
C16: =IF($B16="","",TEXT($B16,"ddd"))
... C44: =IF($B44="","",TEXT($B44,"ddd"))

Sheet Unit_Converter
B2: Maund - Kilogram Converter
B4: 1 maund = 37.32 kilograms (official conversion used throughout this study)
B6: Maunds -> kilograms
B7: Type maund value here | C7: 1
B8: Result - kilograms | C8: =IF(ISNUMBER($C$7),$C$7*37.32,"") -> 37.32
B10: Kilograms -> maunds
B11: Type kg value here | C11: 37.32
B12: Result - maunds | C12: =IF(ISNUMBER($C$11),ROUND($C$11/37.32,4),"") -> 1
B14: Reminder - price flags
B15: K | C15: Species not handled by the respondent today.
B16: D | C16: Price declined - keep the row, the flag itself is information.
B17: 0 / '-' | C17: True zero / not applicable. Empty cells are not allowed in species grids.
B18: Conversion | C18: Blue BDT_per_kg columns convert maund quotes automatically - never type over them.

Sheet Codebook_Species
B2: Species Codebook (Methodology Table 3.4)
B4: Code | C4: Local_name | D4: English_common_name | E4: Scientific_name | F4: Price_tier
B5: S01 | C5: Ilish | D5: Hilsa shad | E5: Tenualosa ilisha | F5: High
B6: S02 | C6: Rupchanda | D6: Silver pomfret | E6: Pampus argenteus | F6: High
B7: S03 | C7: Lakkha | D7: Indian salmon (four-finger threadfin) | E7: Eleutheronema tetradactylum | F7: High
B8: S04 | C8: Koral/Kurl | D8: Asian sea bass | E8: Lates calcarifer | F8: High
B9: S05 | C9: Surma | D9: Indian mackerel | E9: Rastrelliger kanagurta | F9: Medium
B10: S06 | C10: Churi | D10: Largehead ribbonfish | E10: Trichiurus lepturus | F10: Medium
B11: S07 | C11: Poa | D11: Pama croaker | E11: Otolithoides pama | F11: Medium
B12: S08 | C12: Kankoita | D12: Thorny/Indian anchovy | E12: Stolephorus indicus | F12: Low-volume
B13: S09 | C13: Loitta | D13: Bombay duck | E13: Harpadon nehereus | F13: Low
B14: S10 | C14: Harina | D14: Chacunda gizzard shad | E14: Anodontostoma chacunda | F14: Low

Sheet Codebook_Markets
B2: Market Codebook (Methodology Table 3.1)
B4: Code | C4: Market_name | D4: Channel_position | E4: Primary_analytical_contribution
B5: M1 | C5: Fishery Ghat | D5: Landing-linked wholesale-cum-retail | E5: First-sale (producer-side) price observations
B6: M2 | C6: Chawkbazar | D6: Retail | E6: Retail prices and trade volume quotes
B7: M3 | C7: Kazir Dewri | D7: Retail | E7: Retail prices and vendor practices
B8: M4 | C8: Karnaphuli Complex | D8: Retail | E8: Retail prices; comparability with the 2019 baseline
B9: M5 | C9: Bahaddarhat | D9: Retail | E9: Newer-generation retail turnover
B10: M6 | C10: Patenga | D10: Landing-linked retail | E10: Coast-side buy prices supporting producer-share estimation

Sheet Form_A_Aratdar
B2: Form A - Aratdar Questionnaire (one respondent per row)
B4: Respondent_ID | C4: Market | D4: Interview_Date | E4: Age_years | F4: Education | G4: Years_in_business | H4: Daily_capacity_raw | I4: Daily_capacity_unit | J4: Daily_capacity_kg | K4: Family_members | L4: Rent_pay_or_receive | M4: Rent_amount_BDT | N4: Rent_frequency | O4: Commission_basis | P4: Commission_rate | Q4: Electricity_bill_BDT | R4: Electricity_frequency | S4: Workers_count | T4: Worker_daily_wage_BDT | U4: Equipment_Cooler_Maintenance_BDT | V4: Equipment_Cooler_Maintenance_frequency | W4: Other_cost_description | X4: Other_cost_BDT | Y4: Payment_cash_pct | Z4: Payment_MFS_pct | AA4: Payment_credit_pct | AB4: MFS_transaction_frequency | AC4: Problem_1 | AD4: Problem_2 | AE4: Problem_3 | AF4: Pair_ID | AG4: Notes
B5: M1-A-01 | C5: M1 | J5: =IF(OR($H5="",$I5="",NOT(ISNUMBER($H5))),"",IF($I5="Maund",ROUND($H5*37.32,2),$H5))
B6: M1-A-02 | C6: M1 | J6: =IF(OR($H6="",$I6="",NOT(ISNUMBER($H6))),"",IF($I6="Maund",ROUND($H6*37.32,2),$H6))
B7: M1-A-03 | C7: M1 | J7: =IF(OR($H7="",$I7="",NOT(ISNUMBER($H7))),"",IF($I7="Maund",ROUND($H7*37.32,2),$H7))
B8: M1-A-04 | C8: M1 | J8: =IF(OR($H8="",$I8="",NOT(ISNUMBER($H8))),"",IF($I8="Maund",ROUND($H8*37.32,2),$H8))
B9: M1-A-05 | C9: M1 | J9: =IF(OR($H9="",$I9="",NOT(ISNUMBER($H9))),"",IF($I9="Maund",ROUND($H9*37.32,2),$H9))
B10: M1-A-06 | C10: M1 | J10: =IF(OR($H10="",$I10="",NOT(ISNUMBER($H10))),"",IF($I10="Maund",ROUND($H10*37.32,2),$H10))
B11: M2-A-01 | C11: M2 | J11: =IF(OR($H11="",$I11="",NOT(ISNUMBER($H11))),"",IF($I11="Maund",ROUND($H11*37.32,2),$H11))
B12: M2-A-02 | C12: M2 | J12: =IF(OR($H12="",$I12="",NOT(ISNUMBER($H12))),"",IF($I12="Maund",ROUND($H12*37.32,2),$H12))
B13: M2-A-03 | C13: M2 | J13: =IF(OR($H13="",$I13="",NOT(ISNUMBER($H13))),"",IF($I13="Maund",ROUND($H13*37.32,2),$H13))
B14: M2-A-04 | C14: M2 | J14: =IF(OR($H14="",$I14="",NOT(ISNUMBER($H14))),"",IF($I14="Maund",ROUND($H14*37.32,2),$H14))
B15: M2-A-05 | C15: M2 | J15: =IF(OR($H15="",$I15="",NOT(ISNUMBER($H15))),"",IF($I15="Maund",ROUND($H15*37.32,2),$H15))
B16: M2-A-06 | C16: M2 | J16: =IF(OR($H16="",$I16="",NOT(ISNUMBER($H16))),"",IF($I16="Maund",ROUND($H16*37.32,2),$H16))
... B40: M6-A-06 | C40: M6 | J40: =IF(OR($H40="",$I40="",NOT(ISNUMBER($H40))),"",IF($I40="Maund",ROUND($H40*37.32,2),$H40))

Sheet Form_B_Bepari_Faria
B2: Form B - Bepari/Faria Questionnaire (one respondent per row)
B4: Respondent_ID | C4: Market | D4: Interview_Date | E4: Actor_subtype | F4: Business_pattern | G4: Age_years | H4: Education | I4: Years_in_business | J4: Daily_capacity_raw | K4: Daily_capacity_unit | L4: Daily_capacity_kg | M4: Family_members | N4: Source_location | O4: Supplier_category | P4: Transport_fare_per_trip_BDT | Q4: Trip_frequency_days | R4: Trips_per_period | S4: Loading_Unloading_cost_per_trip_BDT | T4: Ice_usage_kg_per_day | U4: Ice_cost_BDT_per_day | V4: Commission_to_aratdar_value | W4: Commission_unit | X4: Transit_damage_pct | Y4: Payment_cash_pct | Z4: Payment_MFS_pct | AA4: Payment_credit_pct | AB4: MFS_transaction_frequency | AC4: Credit_sales_share | AD4: Problem_1 | AE4: Problem_2 | AF4: Problem_3 | AG4: Pair_ID | AH4: Notes
B5: M1-B-01 | C5: M1 | L5: =IF(OR($J5="",$K5="",NOT(ISNUMBER($J5))),"",IF($K5="Maund",ROUND($J5*37.32,2),$J5))
B6: M1-B-02 | C6: M1 | L6: =IF(OR($J6="",$K6="",NOT(ISNUMBER($J6))),"",IF($K6="Maund",ROUND($J6*37.32,2),$J6))
B7: M1-B-03 | C7: M1 | L7: =IF(OR($J7="",$K7="",NOT(ISNUMBER($J7))),"",IF($K7="Maund",ROUND($J7*37.32,2),$J7))
B8: M1-B-04 | C8: M1 | L8: =IF(OR($J8="",$K8="",NOT(ISNUMBER($J8))),"",IF($K8="Maund",ROUND($J8*37.32,2),$J8))
B9: M1-B-05 | C9: M1 | L9: =IF(OR($J9="",$K9="",NOT(ISNUMBER($J9))),"",IF($K9="Maund",ROUND($J9*37.32,2),$J9))
B10: M1-B-06 | C10: M1 | L10: =IF(OR($J10="",$K10="",NOT(ISNUMBER($J10))),"",IF($K10="Maund",ROUND($J10*37.32,2),$J10))
B11: M2-B-01 | C11: M2 | L11: =IF(OR($J11="",$K11="",NOT(ISNUMBER($J11))),"",IF($K11="Maund",ROUND($J11*37.32,2),$J11))
B12: M2-B-02 | C12: M2 | L12: =IF(OR($J12="",$K12="",NOT(ISNUMBER($J12))),"",IF($K12="Maund",ROUND($J12*37.32,2),$J12))
B13: M2-B-03 | C13: M2 | L13: =IF(OR($J13="",$K13="",NOT(ISNUMBER($J13))),"",IF($K13="Maund",ROUND($J13*37.32,2),$J13))
B14: M2-B-04 | C14: M2 | L14: =IF(OR($J14="",$K14="",NOT(ISNUMBER($J14))),"",IF($K14="Maund",ROUND($J14*37.32,2),$J14))
B15: M2-B-05 | C15: M2 | L15: =IF(OR($J15="",$K15="",NOT(ISNUMBER($J15))),"",IF($K15="Maund",ROUND($J15*37.32,2),$J15))
B16: M2-B-06 | C16: M2 | L16: =IF(OR($J16="",$K16="",NOT(ISNUMBER($J16))),"",IF($K16="Maund",ROUND($J16*37.32,2),$J16))
... B40: M6-B-06 | C40: M6 | L40: =IF(OR($J40="",$K40="",NOT(ISNUMBER($J40))),"",IF($K40="Maund",ROUND($J40*37.32,2),$J40))

Sheet Form_R_Khuchra
B2: Form R - Khuchra (Retail) Vendor Questionnaire (one respondent per row)
B4: Respondent_ID | C4: Market | D4: Interview_Date | E4: Age_years | F4: Education | G4: Years_in_business | H4: Daily_capacity_raw | I4: Daily_capacity_unit | J4: Daily_capacity_kg | K4: Family_members | L4: Shop_Van_Rent_BDT_per_day | M4: Ice_cost_BDT_per_day | N4: Wash_Water_Other_cost_BDT_per_day | O4: Spoilage_pct | P4: Buys_from | Q4: Sells_to | R4: Payment_cash_pct | S4: Payment_MFS_pct | T4: Payment_credit_pct | U4: MFS_transaction_frequency | V4: Sells_on_credit | W4: Problem_1 | X4: Problem_2 | Y4: Problem_3 | Z4: Pair_ID | AA4: Notes
B5: M1-R-01 | C5: M1 | J5: =IF(OR($H5="",$I5="",NOT(ISNUMBER($H5))),"",IF($I5="Maund",ROUND($H5*37.32,2),$H5))
B6: M1-R-02 | C6: M1 | J6: =IF(OR($H6="",$I6="",NOT(ISNUMBER($H6))),"",IF($I6="Maund",ROUND($H6*37.32,2),$H6))
B7: M1-R-03 | C7: M1 | J7: =IF(OR($H7="",$I7="",NOT(ISNUMBER($H7))),"",IF($I7="Maund",ROUND($H7*37.32,2),$H7))
B8: M1-R-04 | C8: M1 | J8: =IF(OR($H8="",$I8="",NOT(ISNUMBER($H8))),"",IF($I8="Maund",ROUND($H8*37.32,2),$H8))
B9: M1-R-05 | C9: M1 | J9: =IF(OR($H9="",$I9="",NOT(ISNUMBER($H9))),"",IF($I9="Maund",ROUND($H9*37.32,2),$H9))
B10: M1-R-06 | C10: M1 | J10: =IF(OR($H10="",$I10="",NOT(ISNUMBER($H10))),"",IF($I10="Maund",ROUND($H10*37.32,2),$H10))
B11: M2-R-01 | C11: M2 | J11: =IF(OR($H11="",$I11="",NOT(ISNUMBER($H11))),"",IF($I11="Maund",ROUND($H11*37.32,2),$H11))
B12: M2-R-02 | C12: M2 | J12: =IF(OR($H12="",$I12="",NOT(ISNUMBER($H12))),"",IF($I12="Maund",ROUND($H12*37.32,2),$H12))
B13: M2-R-03 | C13: M2 | J13: =IF(OR($H13="",$I13="",NOT(ISNUMBER($H13))),"",IF($I13="Maund",ROUND($H13*37.32,2),$H13))
B14: M2-R-04 | C14: M2 | J14: =IF(OR($H14="",$I14="",NOT(ISNUMBER($H14))),"",IF($I14="Maund",ROUND($H14*37.32,2),$H14))
B15: M2-R-05 | C15: M2 | J15: =IF(OR($H15="",$I15="",NOT(ISNUMBER($H15))),"",IF($I15="Maund",ROUND($H15*37.32,2),$H15))
B16: M2-R-06 | C16: M2 | J16: =IF(OR($H16="",$I16="",NOT(ISNUMBER($H16))),"",IF($I16="Maund",ROUND($H16*37.32,2),$H16))
... B40: M6-R-06 | C40: M6 | J40: =IF(OR($H40="",$I40="",NOT(ISNUMBER($H40))),"",IF($I40="Maund",ROUND($H40*37.32,2),$H40))

Sheet Form_C_Consumer
B2: Form C - Fish Buyer Exit Slip (one respondent per row)
B4: Respondent_ID | C4: Market | D4: Interview_Date | E4: Interview_time | F4: Consent_given | G4: Visit_frequency | H4: Visit_interval_days | I4: Payment_method | J4: Main_reason_choosing_arat | K4: Pair_ID | L4: Notes
B5: M1-C-01 | C5: M1
B6: M1-C-02 | C6: M1
B7: M1-C-03 | C7: M1
B8: M1-C-04 | C8: M1
B9: M1-C-05 | C9: M1
B10: M1-C-06 | C10: M1
B11: M2-C-01 | C11: M2
B12: M2-C-02 | C12: M2
B13: M2-C-03 | C13: M2
B14: M2-C-04 | C14: M2
B15: M2-C-05 | C15: M2
B16: M2-C-06 | C16: M2
... B40: M6-C-06 | C40: M6

Sheet Price_Observations
B2: Price Observations - one row per respondent x species quote (core dataset)
B4: Obs_ID | C4: Respondent_ID | D4: Market | E4: Actor_type | F4: Species_code | G4: Buy_price_raw | H4: Sell_price_raw | I4: Unit | J4: Buy_BDT_per_kg | K4: Sell_BDT_per_kg | L4: Quantity_raw | M4: Quantity_unit | N4: Quantity_kg | O4: Pair_ID | P4: Notes
B5: PO-0001 | J5: =IF(OR($G5="",$I5="",NOT(ISNUMBER($G5))),"",IF($I5="Maund",ROUND($G5/37.32,2),$G5)) | K5: =IF(OR($H5="",$I5="",NOT(ISNUMBER($H5))),"",IF($I5="Maund",ROUND($H5/37.32,2),$H5)) | N5: =IF(OR($L5="",$M5="",NOT(ISNUMBER($L5))),"",IF($M5="Maund",ROUND($L5*37.32,2),$L5))
B6: PO-0002 | J6: =IF(OR($G6="",$I6="",NOT(ISNUMBER($G6))),"",IF($I6="Maund",ROUND($G6/37.32,2),$G6)) | K6: =IF(OR($H6="",$I6="",NOT(ISNUMBER($H6))),"",IF($I6="Maund",ROUND($H6/37.32,2),$H6)) | N6: =IF(OR($L6="",$M6="",NOT(ISNUMBER($L6))),"",IF($M6="Maund",ROUND($L6*37.32,2),$L6))
B7: PO-0003 | J7: =IF(OR($G7="",$I7="",NOT(ISNUMBER($G7))),"",IF($I7="Maund",ROUND($G7/37.32,2),$G7)) | K7: =IF(OR($H7="",$I7="",NOT(ISNUMBER($H7))),"",IF($I7="Maund",ROUND($H7/37.32,2),$H7)) | N7: =IF(OR($L7="",$M7="",NOT(ISNUMBER($L7))),"",IF($M7="Maund",ROUND($L7*37.32,2),$L7))
B8: PO-0004 | J8: =IF(OR($G8="",$I8="",NOT(ISNUMBER($G8))),"",IF($I8="Maund",ROUND($G8/37.32,2),$G8)) | K8: =IF(OR($H8="",$I8="",NOT(ISNUMBER($H8))),"",IF($I8="Maund",ROUND($H8/37.32,2),$H8)) | N8: =IF(OR($L8="",$M8="",NOT(ISNUMBER($L8))),"",IF($M8="Maund",ROUND($L8*37.32,2),$L8))
B9: PO-0005 | J9: =IF(OR($G9="",$I9="",NOT(ISNUMBER($G9))),"",IF($I9="Maund",ROUND($G9/37.32,2),$G9)) | K9: =IF(OR($H9="",$I9="",NOT(ISNUMBER($H9))),"",IF($I9="Maund",ROUND($H9/37.32,2),$H9)) | N9: =IF(OR($L9="",$M9="",NOT(ISNUMBER($L9))),"",IF($M9="Maund",ROUND($L9*37.32,2),$L9))
B10: PO-0006 | J10: =IF(OR($G10="",$I10="",NOT(ISNUMBER($G10))),"",IF($I10="Maund",ROUND($G10/37.32,2),$G10)) | K10: =IF(OR($H10="",$I10="",NOT(ISNUMBER($H10))),"",IF($I10="Maund",ROUND($H10/37.32,2),$H10)) | N10: =IF(OR($L10="",$M10="",NOT(ISNUMBER($L10))),"",IF($M10="Maund",ROUND($L10*37.32,2),$L10))
B11: PO-0007 | J11: =IF(OR($G11="",$I11="",NOT(ISNUMBER($G11))),"",IF($I11="Maund",ROUND($G11/37.32,2),$G11)) | K11: =IF(OR($H11="",$I11="",NOT(ISNUMBER($H11))),"",IF($I11="Maund",ROUND($H11/37.32,2),$H11)) | N11: =IF(OR($L11="",$M11="",NOT(ISNUMBER($L11))),"",IF($M11="Maund",ROUND($L11*37.32,2),$L11))
B12: PO-0008 | J12: =IF(OR($G12="",$I12="",NOT(ISNUMBER($G12))),"",IF($I12="Maund",ROUND($G12/37.32,2),$G12)) | K12: =IF(OR($H12="",$I12="",NOT(ISNUMBER($H12))),"",IF($I12="Maund",ROUND($H12/37.32,2),$H12)) | N12: =IF(OR($L12="",$M12="",NOT(ISNUMBER($L12))),"",IF($M12="Maund",ROUND($L12*37.32,2),$L12))
B13: PO-0009 | J13: =IF(OR($G13="",$I13="",NOT(ISNUMBER($G13))),"",IF($I13="Maund",ROUND($G13/37.32,2),$G13)) | K13: =IF(OR($H13="",$I13="",NOT(ISNUMBER($H13))),"",IF($I13="Maund",ROUND($H13/37.32,2),$H13)) | N13: =IF(OR($L13="",$M13="",NOT(ISNUMBER($L13))),"",IF($M13="Maund",ROUND($L13*37.32,2),$L13))
B14: PO-0010 | J14: =IF(OR($G14="",$I14="",NOT(ISNUMBER($G14))),"",IF($I14="Maund",ROUND($G14/37.32,2),$G14)) | K14: =IF(OR($H14="",$I14="",NOT(ISNUMBER($H14))),"",IF($I14="Maund",ROUND($H14/37.32,2),$H14)) | N14: =IF(OR($L14="",$M14="",NOT(ISNUMBER($L14))),"",IF($M14="Maund",ROUND($L14*37.32,2),$L14))
B15: PO-0011 | J15: =IF(OR($G15="",$I15="",NOT(ISNUMBER($G15))),"",IF($I15="Maund",ROUND($G15/37.32,2),$G15)) | K15: =IF(OR($H15="",$I15="",NOT(ISNUMBER($H15))),"",IF($I15="Maund",ROUND($H15/37.32,2),$H15)) | N15: =IF(OR($L15="",$M15="",NOT(ISNUMBER($L15))),"",IF($M15="Maund",ROUND($L15*37.32,2),$L15))
B16: PO-0012 | J16: =IF(OR($G16="",$I16="",NOT(ISNUMBER($G16))),"",IF($I16="Maund",ROUND($G16/37.32,2),$G16)) | K16: =IF(OR($H16="",$I16="",NOT(ISNUMBER($H16))),"",IF($I16="Maund",ROUND($H16/37.32,2),$H16)) | N16: =IF(OR($L16="",$M16="",NOT(ISNUMBER($L16))),"",IF($M16="Maund",ROUND($L16*37.32,2),$L16))
... B504: PO-0500 | J504: =IF(OR($G504="",$I504="",NOT(ISNUMBER($G504))),"",IF($I504="Maund",ROUND($G504/37.32,2),$G504)) | K504: =IF(OR($H504="",$I504="",NOT(ISNUMBER($H504))),"",IF($I504="Maund",ROUND($H504/37.32,2),$H504)) | N504: =IF(OR($L504="",$M504="",NOT(ISNUMBER($L504))),"",IF($M504="Maund",ROUND($L504*37.32,2),$L504))
B506: Flags: K = not handled today, D = declined, '-' = not applicable. Blue columns convert maund quotes to BDT/kg automatically (1 maund = 37.32 kg).

Sheet Consumer_Purchases_Focal
B2: Form C - Focal Species Purchases (one row per consumer x species)
B4: Respondent_ID | C4: Market | D4: Species_code | E4: Purchased_today | F4: Bought_from | G4: Price_raw | H4: Unit | I4: Price_BDT_per_kg | J4: Quantity_raw | K4: Quantity_unit | L4: Quantity_kg | M4: Notes
I5: =IF(OR($G5="",$H5="",NOT(ISNUMBER($G5))),"",IF($H5="Maund",ROUND($G5/37.32,2),$G5)) | L5: =IF(OR($J5="",$K5="",NOT(ISNUMBER($J5))),"",IF($K5="Maund",ROUND($J5*37.32,2),$J5))
I6: =IF(OR($G6="",$H6="",NOT(ISNUMBER($G6))),"",IF($H6="Maund",ROUND($G6/37.32,2),$G6)) | L6: =IF(OR($J6="",$K6="",NOT(ISNUMBER($J6))),"",IF($K6="Maund",ROUND($J6*37.32,2),$J6))
I7: =IF(OR($G7="",$H7="",NOT(ISNUMBER($G7))),"",IF($H7="Maund",ROUND($G7/37.32,2),$G7)) | L7: =IF(OR($J7="",$K7="",NOT(ISNUMBER($J7))),"",IF($K7="Maund",ROUND($J7*37.32,2),$J7))
I8: =IF(OR($G8="",$H8="",NOT(ISNUMBER($G8))),"",IF($H8="Maund",ROUND($G8/37.32,2),$G8)) | L8: =IF(OR($J8="",$K8="",NOT(ISNUMBER($J8))),"",IF($K8="Maund",ROUND($J8*37.32,2),$J8))
I9: =IF(OR($G9="",$H9="",NOT(ISNUMBER($G9))),"",IF($H9="Maund",ROUND($G9/37.32,2),$G9)) | L9: =IF(OR($J9="",$K9="",NOT(ISNUMBER($J9))),"",IF($K9="Maund",ROUND($J9*37.32,2),$J9))
I10: =IF(OR($G10="",$H10="",NOT(ISNUMBER($G10))),"",IF($H10="Maund",ROUND($G10/37.32,2),$G10)) | L10: =IF(OR($J10="",$K10="",NOT(ISNUMBER($J10))),"",IF($K10="Maund",ROUND($J10*37.32,2),$J10))
I11: =IF(OR($G11="",$H11="",NOT(ISNUMBER($G11))),"",IF($H11="Maund",ROUND($G11/37.32,2),$G11)) | L11: =IF(OR($J11="",$K11="",NOT(ISNUMBER($J11))),"",IF($K11="Maund",ROUND($J11*37.32,2),$J11))
I12: =IF(OR($G12="",$H12="",NOT(ISNUMBER($G12))),"",IF($H12="Maund",ROUND($G12/37.32,2),$G12)) | L12: =IF(OR($J12="",$K12="",NOT(ISNUMBER($J12))),"",IF($K12="Maund",ROUND($J12*37.32,2),$J12))
I13: =IF(OR($G13="",$H13="",NOT(ISNUMBER($G13))),"",IF($H13="Maund",ROUND($G13/37.32,2),$G13)) | L13: =IF(OR($J13="",$K13="",NOT(ISNUMBER($J13))),"",IF($K13="Maund",ROUND($J13*37.32,2),$J13))
I14: =IF(OR($G14="",$H14="",NOT(ISNUMBER($G14))),"",IF($H14="Maund",ROUND($G14/37.32,2),$G14)) | L14: =IF(OR($J14="",$K14="",NOT(ISNUMBER($J14))),"",IF($K14="Maund",ROUND($J14*37.32,2),$J14))
I15: =IF(OR($G15="",$H15="",NOT(ISNUMBER($G15))),"",IF($H15="Maund",ROUND($G15/37.32,2),$G15)) | L15: =IF(OR($J15="",$K15="",NOT(ISNUMBER($J15))),"",IF($K15="Maund",ROUND($J15*37.32,2),$J15))
I16: =IF(OR($G16="",$H16="",NOT(ISNUMBER($G16))),"",IF($H16="Maund",ROUND($G16/37.32,2),$G16)) | L16: =IF(OR($J16="",$K16="",NOT(ISNUMBER($J16))),"",IF($K16="Maund",ROUND($J16*37.32,2),$J16))
... I354: =IF(OR($G354="",$H354="",NOT(ISNUMBER($G354))),"",IF($H354="Maund",ROUND($G354/37.32,2),$G354)) | L354: =IF(OR($J354="",$K354="",NOT(ISNUMBER($J354))),"",IF($K354="Maund",ROUND($J354*37.32,2),$J354))

Sheet Consumer_Other_Fish
B2: Form C - Any Other Fish Bought (long format)
B4: Respondent_ID | C4: Market | D4: Fish_name_local | E4: Price_raw | F4: Unit | G4: Price_BDT_per_kg | H4: Quantity_raw | I4: Quantity_unit | J4: Quantity_kg | K4: Purchase_location | L4: Notes
G5: =IF(OR($E5="",$F5="",NOT(ISNUMBER($E5))),"",IF($F5="Maund",ROUND($E5/37.32,2),$E5)) | J5: =IF(OR($H5="",$I5="",NOT(ISNUMBER($H5))),"",IF($I5="Maund",ROUND($H5*37.32,2),$H5))
G6: =IF(OR($E6="",$F6="",NOT(ISNUMBER($E6))),"",IF($F6="Maund",ROUND($E6/37.32,2),$E6)) | J6: =IF(OR($H6="",$I6="",NOT(ISNUMBER($H6))),"",IF($I6="Maund",ROUND($H6*37.32,2),$H6))
G7: =IF(OR($E7="",$F7="",NOT(ISNUMBER($E7))),"",IF($F7="Maund",ROUND($E7/37.32,2),$E7)) | J7: =IF(OR($H7="",$I7="",NOT(ISNUMBER($H7))),"",IF($I7="Maund",ROUND($H7*37.32,2),$H7))
G8: =IF(OR($E8="",$F8="",NOT(ISNUMBER($E8))),"",IF($F8="Maund",ROUND($E8/37.32,2),$E8)) | J8: =IF(OR($H8="",$I8="",NOT(ISNUMBER($H8))),"",IF($I8="Maund",ROUND($H8*37.32,2),$H8))
G9: =IF(OR($E9="",$F9="",NOT(ISNUMBER($E9))),"",IF($F9="Maund",ROUND($E9/37.32,2),$E9)) | J9: =IF(OR($H9="",$I9="",NOT(ISNUMBER($H9))),"",IF($I9="Maund",ROUND($H9*37.32,2),$H9))
G10: =IF(OR($E10="",$F10="",NOT(ISNUMBER($E10))),"",IF($F10="Maund",ROUND($E10/37.32,2),$E10)) | J10: =IF(OR($H10="",$I10="",NOT(ISNUMBER($H10))),"",IF($I10="Maund",ROUND($H10*37.32,2),$H10))
G11: =IF(OR($E11="",$F11="",NOT(ISNUMBER($E11))),"",IF($F11="Maund",ROUND($E11/37.32,2),$E11)) | J11: =IF(OR($H11="",$I11="",NOT(ISNUMBER($H11))),"",IF($I11="Maund",ROUND($H11*37.32,2),$H11))
G12: =IF(OR($E12="",$F12="",NOT(ISNUMBER($E12))),"",IF($F12="Maund",ROUND($E12/37.32,2),$E12)) | J12: =IF(OR($H12="",$I12="",NOT(ISNUMBER($H12))),"",IF($I12="Maund",ROUND($H12*37.32,2),$H12))
G13: =IF(OR($E13="",$F13="",NOT(ISNUMBER($E13))),"",IF($F13="Maund",ROUND($E13/37.32,2),$E13)) | J13: =IF(OR($H13="",$I13="",NOT(ISNUMBER($H13))),"",IF($I13="Maund",ROUND($H13*37.32,2),$H13))
G14: =IF(OR($E14="",$F14="",NOT(ISNUMBER($E14))),"",IF($F14="Maund",ROUND($E14/37.32,2),$E14)) | J14: =IF(OR($H14="",$I14="",NOT(ISNUMBER($H14))),"",IF($I14="Maund",ROUND($H14*37.32,2),$H14))
G15: =IF(OR($E15="",$F15="",NOT(ISNUMBER($E15))),"",IF($F15="Maund",ROUND($E15/37.32,2),$E15)) | J15: =IF(OR($H15="",$I15="",NOT(ISNUMBER($H15))),"",IF($I15="Maund",ROUND($H15*37.32,2),$H15))
G16: =IF(OR($E16="",$F16="",NOT(ISNUMBER($E16))),"",IF($F16="Maund",ROUND($E16/37.32,2),$E16)) | J16: =IF(OR($H16="",$I16="",NOT(ISNUMBER($H16))),"",IF($I16="Maund",ROUND($H16*37.32,2),$H16))
... G104: =IF(OR($E104="",$F104="",NOT(ISNUMBER($E104))),"",IF($F104="Maund",ROUND($E104/37.32,2),$E104)) | J104: =IF(OR($H104="",$I104="",NOT(ISNUMBER($H104))),"",IF($I104="Maund",ROUND($H104*37.32,2),$H104))

Sheet Form_M_Market_Observation
B2: Form M - Market Observation Checklist (one row per market)
B4: Market | C4: Market_name | D4: Obs_Date | E4: Market_type | F4: Trading_hours | G4: Retail_stall_count | H4: Transport_access | I4: Platform_condition | J4: Roofing | K4: Drainage | L4: Electricity | M4: Ice_availability | N4: Ice_distance_note | O4: Sanitation | P4: Water_supply | Q4: Fee_arrangement | R4: Fee_rate_note | S4: GPS_coordinates | T4: Photo_references | U4: Evidence_source_note
B5: M1 | C5: Fishery Ghat
B6: M2 | C6: Chawkbazar
B7: M3 | C7: Kazir Dewri
B8: M4 | C8: Karnaphuli Complex
B9: M5 | C9: Bahaddarhat
B10: M6 | C10: Patenga
B12: Twelve infrastructure items graded Good/Medium/Poor, Complete/Partial/None or Regular/Irregular/None as applicable (Methodology 3.5).

Sheet Tag_Price_Sheet
B2: Tag Price Sheet - displayed prices of all fish seen (optional, appendix only)
B4: Date | C4: Market | D4: Shop_or_Vendor_No | E4: Collector_initials | F4: Fish_name_local | G4: Price_raw | H4: Unit | I4: Price_BDT_per_kg | J4: Notes
I5: =IF(OR($G5="",$H5="",NOT(ISNUMBER($G5))),"",IF($H5="Maund",ROUND($G5/37.32,2),$G5))
I6: =IF(OR($G6="",$H6="",NOT(ISNUMBER($G6))),"",IF($H6="Maund",ROUND($G6/37.32,2),$G6))
I7: =IF(OR($G7="",$H7="",NOT(ISNUMBER($G7))),"",IF($H7="Maund",ROUND($G7/37.32,2),$G7))
I8: =IF(OR($G8="",$H8="",NOT(ISNUMBER($G8))),"",IF($H8="Maund",ROUND($G8/37.32,2),$G8))
I9: =IF(OR($G9="",$H9="",NOT(ISNUMBER($G9))),"",IF($H9="Maund",ROUND($G9/37.32,2),$G9))
I10: =IF(OR($G10="",$H10="",NOT(ISNUMBER($G10))),"",IF($H10="Maund",ROUND($G10/37.32,2),$G10))
I11: =IF(OR($G11="",$H11="",NOT(ISNUMBER($G11))),"",IF($H11="Maund",ROUND($G11/37.32,2),$G11))
I12: =IF(OR($G12="",$H12="",NOT(ISNUMBER($G12))),"",IF($H12="Maund",ROUND($G12/37.32,2),$G12))
I13: =IF(OR($G13="",$H13="",NOT(ISNUMBER($G13))),"",IF($H13="Maund",ROUND($G13/37.32,2),$G13))
I14: =IF(OR($G14="",$H14="",NOT(ISNUMBER($G14))),"",IF($H14="Maund",ROUND($G14/37.32,2),$G14))
I15: =IF(OR($G15="",$H15="",NOT(ISNUMBER($G15))),"",IF($H15="Maund",ROUND($G15/37.32,2),$G15))
I16: =IF(OR($G16="",$H16="",NOT(ISNUMBER($G16))),"",IF($H16="Maund",ROUND($G16/37.32,2),$G16))
... I324: =IF(OR($G324="",$H324="",NOT(ISNUMBER($G324))),"",IF($H324="Maund",ROUND($G324/37.32,2),$G324))
B326: Spend ~10 minutes per arat listing every displayed price; never enters hypothesis tests, appendix descriptive table only.

Sheet QC_Check
B2: QC Check - automatic quality flags
B3: Everything on this sheet is formula-driven. Re-check after each entry session; fix the source sheet, never this one.
B5: Check | C5: Value | D5: Rule / target | E5: Status
B6: Form_A rows entered (Interview_Date filled) | C6: =COUNTIF(Form_A_Aratdar!$D$5:$D$40,"<>") -> 0 | D6: 36 rows allocated (quota 30 + buffer 6) | E6: =IF(C6<=36,"OK","Over capacity") -> OK
B7: Form_B rows entered (Interview_Date filled) | C7: =COUNTIF(Form_B_Bepari_Faria!$D$5:$D$40,"<>") -> 0 | D7: 36 rows allocated (quota 30 + buffer 6) | E7: =IF(C7<=36,"OK","Over capacity") -> OK
B8: Form_R rows entered (Interview_Date filled) | C8: =COUNTIF(Form_R_Khuchra!$D$5:$D$40,"<>") -> 0 | D8: 36 rows allocated (quota 30 + buffer 6) | E8: =IF(C8<=36,"OK","Over capacity") -> OK
B9: Form_C rows entered (Interview_Date filled) | C9: =COUNTIF(Form_C_Consumer!$D$5:$D$40,"<>") -> 0 | D9: 36 rows allocated (quota 30 + buffer 6) | E9: =IF(C9<=36,"OK","Over capacity") -> OK
B10: Total interviews entered | C10: =Progress_Dashboard!$G$12 -> 0 | D10: Field target 120 (Table 3.3) | E10: =IF(C10=120,"TARGET MET",IF(C10<120,"In progress","Over quota")) -> In progress
B11: Duplicate Respondent_IDs - Form_A_Aratdar | C11: =SUMPRODUCT((Form_A_Aratdar!$B$5:$B$40<>"")*(COUNTIF(Form_A_Aratdar!$B$5:$B$40,Form_A_Aratdar!$B$5:$B$40)>1)) -> 0 | D11: 0 duplicates expected | E11: =IF(C11=0,"OK","Fix duplicates") -> OK
B12: Duplicate Respondent_IDs - Form_B_Bepari_Faria | C12: =SUMPRODUCT((Form_B_Bepari_Faria!$B$5:$B$40<>"")*(COUNTIF(Form_B_Bepari_Faria!$B$5:$B$40,Form_B_Bepari_Faria!$B$5:$B$40)>1)) -> 0 | D12: 0 duplicates expected | E12: =IF(C12=0,"OK","Fix duplicates") -> OK
B13: Duplicate Respondent_IDs - Form_R_Khuchra | C13: =SUMPRODUCT((Form_R_Khuchra!$B$5:$B$40<>"")*(COUNTIF(Form_R_Khuchra!$B$5:$B$40,Form_R_Khuchra!$B$5:$B$40)>1)) -> 0 | D13: 0 duplicates expected | E13: =IF(C13=0,"OK","Fix duplicates") -> OK
B14: Duplicate Respondent_IDs - Form_C_Consumer | C14: =SUMPRODUCT((Form_C_Consumer!$B$5:$B$40<>"")*(COUNTIF(Form_C_Consumer!$B$5:$B$40,Form_C_Consumer!$B$5:$B$40)>1)) -> 0 | D14: 0 duplicates expected | E14: =IF(C14=0,"OK","Fix duplicates") -> OK
B15: Payment % rows not summing to 100 - Form_A | C15: =SUMPRODUCT((Form_A_Aratdar!$Y$5:$Y$40<>"")*((Form_A_Aratdar!$Y$5:$Y$40+Form_A_Aratdar!$Z$5:$Z$40+Form_A_Aratdar!$AA$5:$AA$40)<>100)) -> 0 | D15: Cash + MFS + Credit must equal 100 | E15: =IF(C15=0,"OK","Check rows") -> OK
B16: Payment % rows not summing to 100 - Form_B | C16: =SUMPRODUCT((Form_B_Bepari_Faria!$Y$5:$Y$40<>"")*((Form_B_Bepari_Faria!$Y$5:$Y$40+Form_B_Bepari_Faria!$Z$5:$Z$40+Form_B_Bepari_Faria!$AA$5:$AA$40)<>100)) -> 0 | D16: Cash + MFS + Credit must equal 100 | E16: =IF(C16=0,"OK","Check rows") -> OK
B17: Payment % rows not summing to 100 - Form_R | C17: =SUMPRODUCT((Form_R_Khuchra!$R$5:$R$40<>"")*((Form_R_Khuchra!$R$5:$R$40+Form_R_Khuchra!$S$5:$S$40+Form_R_Khuchra!$T$5:$T$40)<>100)) -> 0 | D17: Cash + MFS + Credit must equal 100 | E17: =IF(C17=0,"OK","Check rows") -> OK
B18: Price_Observations: numeric BUY price but Unit empty | C18: =SUMPRODUCT((ISNUMBER(Price_Observations!$G$5:$G$504))*(Price_Observations!$I$5:$I$504="")) -> 0 | D18: Every numeric raw price needs Maund/Kg | E18: =IF(C18=0,"OK","Fill Unit column") -> OK
B19: Price_Observations: numeric SELL price but Unit empty | C19: =SUMPRODUCT((ISNUMBER(Price_Observations!$H$5:$H$504))*(Price_Observations!$I$5:$I$504="")) -> 0 | D19: Every numeric raw price needs Maund/Kg | E19: =IF(C19=0,"OK","Fill Unit column") -> OK
B20: Price_Observations rows with unknown Respondent_ID | C20: =SUMPRODUCT((Price_Observations!$C$5:$C$504<>"")*((COUNTIF(Form_A_Aratdar!$B$5:$B$40,Price_Observations!$C$5:$C$504)+COUNTIF(Form_B_Bepari_Faria!$B$5:$B$40,Price_Observations!$C$5:$C$504)+COUNTIF(Form_R_Khuchra!$B$5:$B$40,Price_Observations!$C$5:$C$504))=0)) -> 0 | D20: IDs must exist on Form_A/B/R | E20: =IF(C20=0,"OK","Fix IDs") -> OK
B21: Consumer_Purchases_Focal: numeric price but Unit empty | C21: =SUMPRODUCT((ISNUMBER(Consumer_Purchases_Focal!$G$5:$G$354))*(Consumer_Purchases_Focal!$H$5:$H$354="")) -> 0 | D21: Every numeric raw price needs Maund/Kg | E21: =IF(C21=0,"OK","Fill Unit column") -> OK
B22: Consumer_Other_Fish: numeric price but Unit empty | C22: =SUMPRODUCT((ISNUMBER(Consumer_Other_Fish!$E$5:$E$104))*(Consumer_Other_Fish!$F$5:$F$104="")) -> 0 | D22: Every numeric raw price needs Maund/Kg | E22: =IF(C22=0,"OK","Fill Unit column") -> OK
B23: Consumer_Purchases_Focal rows with unknown Respondent_ID | C23: =SUMPRODUCT((Consumer_Purchases_Focal!$B$5:$B$354<>"")*(COUNTIF(Form_C_Consumer!$B$5:$B$40,Consumer_Purchases_Focal!$B$5:$B$354)=0)) -> 0 | D23: IDs must exist on Form_C | E23: =IF(C23=0,"OK","Fix IDs") -> OK
B24: Consumer_Other_Fish rows with unknown Respondent_ID | C24: =SUMPRODUCT((Consumer_Other_Fish!$B$5:$B$104<>"")*(COUNTIF(Form_C_Consumer!$B$5:$B$40,Consumer_Other_Fish!$B$5:$B$104)=0)) -> 0 | D24: IDs must exist on Form_C | E24: =IF(C24=0,"OK","Fix IDs") -> OK
B25: K/D flags used - buy price column (information) | C25: =COUNTIF(Price_Observations!$G$5:$G$504,"K")+COUNTIF(Price_Observations!$G$5:$G$504,"D") -> 0 | D25: Flags are valid data, no action needed | E25: ="Info" -> Info
B26: K/D flags used - sell price column (information) | C26: =COUNTIF(Price_Observations!$H$5:$H$504,"K")+COUNTIF(Price_Observations!$H$5:$H$504,"D") -> 0 | D26: Flags are valid data, no action needed | E26: ="Info" -> Info
B27: Price_Observations rows carrying a Pair_ID | C27: =COUNTIF(Price_Observations!$O$5:$O$504,"<>") -> 0 | D27: Matched buyer-seller pairs (Methodology 3.3.4) | E27: ="Info" -> Info
B28: Price Pair_IDs matched to a trader Pair_ID | C28: =SUMPRODUCT((Price_Observations!$O$5:$O$504<>"")*((COUNTIF(Form_A_Aratdar!$AF$5:$AF$40,Price_Observations!$O$5:$O$504)+COUNTIF(Form_B_Bepari_Faria!$AG$5:$AG$40,Price_Observations!$O$5:$O$504)+COUNTIF(Form_R_Khuchra!$Z$5:$Z$40,Price_Observations!$O$5:$O$504))>0)) -> 0 | D28: Each price Pair_ID should appear on a trader form | E28: =IF(C27=0,"No pairs yet",IF(C28=C27,"All matched","Some unmatched")) -> No pairs yet
B29: Form_M completed (markets observed) | C29: =COUNTIF(Form_M_Market_Observation!$D$5:$D$10,"<>") -> 0 | D29: 6 markets | E29: =IF(C29=6,"COMPLETE","In progress") -> In progress
B31: Tip: use the filter arrows on each form sheet to find flagged rows (e.g. filter Respondent_ID, or sort by the offending column).
