Workbook

Sheet Instructions
B2: Marine Fish Marketing Survey - Data Entry Workbook
B3: MS-499 term paper - marketing system of commercially important marine fish species, Chattogram region. Fill only YELLOW cells; BLUE columns calculate themselves; GREY cells are prefilled codes.
B5: 1. Sheet map
B6: Progress_Dashboard | C6: Collected vs target counts per market and actor class - updates by itself, never type here.
B7: Data_Collection_Log | C7: One row per field visit: date, market, collector, session, reference-day flag, interviews done.
B8: Unit_Converter | C8: Type a maund value and read kilograms (and the reverse) using 1 maund = 37.32 kg.
B9: Codebook_Species / Codebook_Markets | C9: Official codes S01-S10 and M1-M6. Use codes everywhere; keep these sheets unchanged.
B10: Form_A_Aratdar / Form_B_Bepari_Faria / Form_R_Khuchra | C10: Trader questionnaires - one respondent per row, IDs already assigned (M1-A-01 ... M6-C-06).
B11: Form_C_Consumer | C11: Exit-intercept consumer slips - one respondent per row.
B12: Price_Observations | C12: CORE dataset: one row per respondent x species quote (buy and sell price, quantity). This sheet feeds the R analysis.
B13: Consumer_Purchases_Focal / Consumer_Other_Fish | C13: Form C species grid and 'any other fish bought' answers, long format.
B14: Form_M_Market_Observation | C14: One row per market - the 12-item infrastructure checklist with evidence source.
B15: Tag_Price_Sheet | C15: Optional displayed-price log (appendix only, not used in hypothesis tests).
B16: QC_Check | C16: Automatic quality flags: duplicates, % sums, missing units, PairID linkage. Review after every entry session.
B18: 2. Price-cell flags (all price columns)
B19: Number (e.g. 850) | C19: BDT price under today's fresh, ice-touched, whole-fish condition.
B20: K | C20: Respondent did not handle this species today.
B21: D | C21: Respondent declined to disclose the price.
B22: 0 and '-' | C22: 0 = true zero (rare); '-' = not applicable. Never leave a species cell empty.
B24: 3. Units, IDs and percentages
B25: Units | C25: Enter the price exactly as quoted (Raw) and pick the unit. Traders usually quote per MAUND (1 maund = 37.32 kg), consumers per KG. The BLUE BDT_per_kg columns convert automatically - do not type in them.
B26: Respondent_ID | C26: Prefilled: {Market}-{Actor}-{Serial}, e.g. M1-A-01, M2-B-05, M3-R-12, M4-C-03. Actor codes: A = aratdar, B = bepari/faria, R = khuchra retailer, C = consumer.
B27: Pair_ID | C27: When a buyer and the matching seller are BOTH interviewed, write the same Pair_ID (e.g. PAIR-001) on both rows. Used for the Wilcoxon signed-rank consistency check.
B28: Percent columns | C28: Enter plain numbers 0-100 (70 means 70%). Cash + MFS + Credit should sum to 100 - QC_Check flags mismatches.
B30: 4. Example entries (illustrations only - do not paste)
B31: Form_A row: | C31: M1-A-01 | M1 | 05/03/2026 | age 46 | Secondary | 18 yrs business | 12 Maund/day | family 6 | rent: Pay, 48000 Yearly | commission: 2.5 Percent | waste 500 Monthly | 6 workers x 700 BDT | storage 2500 Yearly | payment 85 / 10 / 5 | MFS: Regular | problems: ice price, toll, unsold loss
B32: Price_Observations rows: | C32: PO-0001 | M1-A-01 | M1 | Aratdar | S01 | buy 32000 Maund, sell 33500 Maund -> auto 857.45 / 897.64 BDT/kg | qty 8 Maund PO-0002 | M3-R-04 | M3 | Retailer | S06 | buy 240 Kg, sell K (no sale today) | qty 15 Kg
B34: Version 2026-08 | Built for the Methodology V4 instrument battery (Forms A, B, R, M, C + optional tag-price sheet).
B36: সংস্করণ ২ (আপডেট) — ফর্ম-নির্ভুল পরিবর্তন
C37: Form_A: বিদ্যুৎ বিল (Electricity_bill_BDT) ও যন্ত্রাংশ/কুল রক্ষণাবেক্ষণ (Equipment_Cooler_Maintenance_BDT) কলাম সঠিক নামে ঠিক করা হয়েছে।
C38: Form_B: দৈনিক হ্যান্ডেল (কেজি/দিন) কলাম যোগ হয়েছে (আগে বাদ ছিল); লোডিং+আনলোডিং খরচ একটি কলামে মেশানো হয়েছে; পরিবহন ভাড়া এখন "প্রতি ট্রিপ" ভিত্তিতে + ট্রিপের হার (প্রতি কত দিনে কয় ট্রিপ); Transport_mode কলাম বাদ দেওয়া হয়েছে (মূল ফর্মে নেই)।
C39: Form_R: দোকান ভাড়া/বরফ/ধোয়া-পানি খরচ এখন প্রতি-দিন (BDT/day) ভিত্তিতে, আগে ভুলবশত মাসিক ছিল।
C40: Form_C: পেমেন্ট মেথড ও বাজার-পছন্দের কারণের অপশন তালিকা মূল ফর্মের সাথে হুবহু মেলানো হয়েছে (নগদ/বিকাশ/নগদ-অ্যাপ/বাকি; দাম/বৈচিত্র্য/নৈকট্য/বিশুদ্ধতা/পরিচিত দোকান)।
C41: Consumer_Purchases_Focal ও Price_Observations: বিক্রেতা/actor তালিকা মূল ফর্মের ভাষার সাথে মেলানো হয়েছে (খুচরা/ফেরিওয়ালা; Khuchra)।
C42: Progress_Dashboard ও QC_Check-এর সূত্র নতুন কলাম-অবস্থান অনুযায়ী আপডেট করা হয়েছে — কিছু হাতে ঠিক করার দরকার নেই।

Sheet Progress_Dashboard
B2: Field Progress Dashboard - target 120 respondents across 6 markets
B3: Counts update automatically from the Interview_Date column of each form sheet. Never type in this sheet.
B5: Market | C5: Aratdar (5) | D5: Bepari/Faria (5) | E5: Retailer (5) | F5: Consumer (5) | G5: Market total (20) | H5: Form M done
B6: M1 | C6: =COUNTIFS(Form_A_Aratdar!$C$5:$C$40,$B6,Form_A_Aratdar!$D$5:$D$40,"<>") | D6: =COUNTIFS(Form_B_Bepari_Faria!$C$5:$C$40,$B6,Form_B_Bepari_Faria!$D$5:$D$40,"<>") | E6: =COUNTIFS(Form_R_Khuchra!$C$5:$C$40,$B6,Form_R_Khuchra!$D$5:$D$40,"<>") | F6: =COUNTIFS(Form_C_Consumer!$C$5:$C$40,$B6,Form_C_Consumer!$D$5:$D$40,"<>") | G6: =SUM(C6:F6) | H6: =IF(COUNTIFS(Form_M_Market_Observation!$B$5:$B$10,$B6,Form_M_Market_Observation!$D$5:$D$10,"<>")>0,"Yes","No")
B7: M2 | C7: =COUNTIFS(Form_A_Aratdar!$C$5:$C$40,$B7,Form_A_Aratdar!$D$5:$D$40,"<>") | D7: =COUNTIFS(Form_B_Bepari_Faria!$C$5:$C$40,$B7,Form_B_Bepari_Faria!$D$5:$D$40,"<>") | E7: =COUNTIFS(Form_R_Khuchra!$C$5:$C$40,$B7,Form_R_Khuchra!$D$5:$D$40,"<>") | F7: =COUNTIFS(Form_C_Consumer!$C$5:$C$40,$B7,Form_C_Consumer!$D$5:$D$40,"<>") | G7: =SUM(C7:F7) | H7: =IF(COUNTIFS(Form_M_Market_Observation!$B$5:$B$10,$B7,Form_M_Market_Observation!$D$5:$D$10,"<>")>0,"Yes","No")
B8: M3 | C8: =COUNTIFS(Form_A_Aratdar!$C$5:$C$40,$B8,Form_A_Aratdar!$D$5:$D$40,"<>") | D8: =COUNTIFS(Form_B_Bepari_Faria!$C$5:$C$40,$B8,Form_B_Bepari_Faria!$D$5:$D$40,"<>") | E8: =COUNTIFS(Form_R_Khuchra!$C$5:$C$40,$B8,Form_R_Khuchra!$D$5:$D$40,"<>") | F8: =COUNTIFS(Form_C_Consumer!$C$5:$C$40,$B8,Form_C_Consumer!$D$5:$D$40,"<>") | G8: =SUM(C8:F8) | H8: =IF(COUNTIFS(Form_M_Market_Observation!$B$5:$B$10,$B8,Form_M_Market_Observation!$D$5:$D$10,"<>")>0,"Yes","No")
B9: M4 | C9: =COUNTIFS(Form_A_Aratdar!$C$5:$C$40,$B9,Form_A_Aratdar!$D$5:$D$40,"<>") | D9: =COUNTIFS(Form_B_Bepari_Faria!$C$5:$C$40,$B9,Form_B_Bepari_Faria!$D$5:$D$40,"<>") | E9: =COUNTIFS(Form_R_Khuchra!$C$5:$C$40,$B9,Form_R_Khuchra!$D$5:$D$40,"<>") | F9: =COUNTIFS(Form_C_Consumer!$C$5:$C$40,$B9,Form_C_Consumer!$D$5:$D$40,"<>") | G9: =SUM(C9:F9) | H9: =IF(COUNTIFS(Form_M_Market_Observation!$B$5:$B$10,$B9,Form_M_Market_Observation!$D$5:$D$10,"<>")>0,"Yes","No")
B10: M5 | C10: =COUNTIFS(Form_A_Aratdar!$C$5:$C$40,$B10,Form_A_Aratdar!$D$5:$D$40,"<>") | D10: =COUNTIFS(Form_B_Bepari_Faria!$C$5:$C$40,$B10,Form_B_Bepari_Faria!$D$5:$D$40,"<>") | E10: =COUNTIFS(Form_R_Khuchra!$C$5:$C$40,$B10,Form_R_Khuchra!$D$5:$D$40,"<>") | F10: =COUNTIFS(Form_C_Consumer!$C$5:$C$40,$B10,Form_C_Consumer!$D$5:$D$40,"<>") | G10: =SUM(C10:F10) | H10: =IF(COUNTIFS(Form_M_Market_Observation!$B$5:$B$10,$B10,Form_M_Market_Observation!$D$5:$D$10,"<>")>0,"Yes","No")
B11: M6 | C11: =COUNTIFS(Form_A_Aratdar!$C$5:$C$40,$B11,Form_A_Aratdar!$D$5:$D$40,"<>") | D11: =COUNTIFS(Form_B_Bepari_Faria!$C$5:$C$40,$B11,Form_B_Bepari_Faria!$D$5:$D$40,"<>") | E11: =COUNTIFS(Form_R_Khuchra!$C$5:$C$40,$B11,Form_R_Khuchra!$D$5:$D$40,"<>") | F11: =COUNTIFS(Form_C_Consumer!$C$5:$C$40,$B11,Form_C_Consumer!$D$5:$D$40,"<>") | G11: =SUM(C11:F11) | H11: =IF(COUNTIFS(Form_M_Market_Observation!$B$5:$B$10,$B11,Form_M_Market_Observation!$D$5:$D$10,"<>")>0,"Yes","No")
B12: TOTAL | C12: =SUM(C6:C11) | D12: =SUM(D6:D11) | E12: =SUM(E6:E11) | F12: =SUM(F6:F11) | G12: =SUM(G6:G11) | H12: =IF(G12=120,"TARGET MET","In progress")
B14: Dataset progress
B15: Interviews entered (of 120) | C15: =G12
B16: Target reached (%) | C16: =G12/120
B17: Price_Observations rows entered | C17: =COUNTIF(Price_Observations!$C$5:$C$504,"<>")
B18: of which Aratdar quotes | C18: =COUNTIF(Price_Observations!$E$5:$E$504,"Aratdar")
B19: of which Bepari/Faria quotes | C19: =COUNTIF(Price_Observations!$E$5:$E$504,"Bepari_Faria")
B20: of which Retailer quotes | C20: =COUNTIF(Price_Observations!$E$5:$E$504,"Khuchra")
B21: Consumer_Purchases_Focal rows entered | C21: =COUNTIF(Consumer_Purchases_Focal!$B$5:$B$354,"<>")
B22: Consumer_Other_Fish rows entered | C22: =COUNTIF(Consumer_Other_Fish!$B$5:$B$104,"<>")
B23: Tag_Price_Sheet rows entered (optional) | C23: =COUNTIF(Tag_Price_Sheet!$C$5:$C$324,"<>")
B24: Data_Collection_Log days used | C24: =COUNTIF(Data_Collection_Log!$B$5:$B$44,"<>")
B26: Quota per market: 5 aratdar + 5 bepari/faria + 5 khuchra retailers + 5 consumers (Methodology Table 3.3).

Sheet Data_Collection_Log
B2: Data Collection Log - one row per field visit
B4: Date | C4: Weekday | D4: Market | E4: Collector_name | F4: Session_start | G4: Session_end | H4: Ref_day_prices_used | I4: Traders_interviewed | J4: Consumers_interviewed | K4: Weather_notes | L4: Notes
B5: 46083 | C5: =IF($B5="","",TEXT($B5,"ddd")) | D5: M1 | E5: Field Team A | F5: 05:30 | G5: 09:00 | H5: No | I5: 4 | J5: 1 | K5: Light fog, calm sea | L5: Pilot day - Chattogram
B6: 46084 | C6: =IF($B6="","",TEXT($B6,"ddd")) | D6: M1 | E6: Field Team A | F6: 04:30 | G6: 09:00 | H6: No | I6: 15 | J6: 5 | K6: Fair, moderate NE wind | L6: Fishery Ghat landing - main round
B7: 46084 | C7: =IF($B7="","",TEXT($B7,"ddd")) | D7: M6 | E7: Field Team B | F7: 09:45 | G7: 13:30 | H7: No | I7: 15 | J7: 5 | K7: Sunny | L7: Patenga landing
B8: 46085 | C8: =IF($B8="","",TEXT($B8,"ddd")) | D8: M2 | E8: Field Team A | F8: 07:00 | G8: 11:30 | H8: No | I8: 15 | J8: 5 | K8: Sunny and humid | L8: Chawkbazar retail
B9: 46086 | C9: =IF($B9="","",TEXT($B9,"ddd")) | D9: M3 | E9: Field Team B | F9: 07:30 | G9: 12:00 | H9: No | I9: 15 | J9: 5 | K9: Overcast | L9: Kazir Dewri
B10: 46087 | C10: =IF($B10="","",TEXT($B10,"ddd")) | D10: M4 | E10: Field Team A | F10: 06:30 | G10: 10:30 | H10: Yes | I10: 15 | J10: 5 | K10: Hot, 33C | L10: Karnaphuli Complex
B11: 46088 | C11: =IF($B11="","",TEXT($B11,"ddd")) | D11: M5 | E11: Field Team B | F11: 07:00 | G11: 11:30 | H11: No | I11: 15 | J11: 5 | K11: Fair | L11: Bahaddarhat
C12: =IF($B12="","",TEXT($B12,"ddd"))
C13: =IF($B13="","",TEXT($B13,"ddd"))
C14: =IF($B14="","",TEXT($B14,"ddd"))
C15: =IF($B15="","",TEXT($B15,"ddd"))
C16: =IF($B16="","",TEXT($B16,"ddd"))
C17: =IF($B17="","",TEXT($B17,"ddd"))
C18: =IF($B18="","",TEXT($B18,"ddd"))
C19: =IF($B19="","",TEXT($B19,"ddd"))
C20: =IF($B20="","",TEXT($B20,"ddd"))
C21: =IF($B21="","",TEXT($B21,"ddd"))
C22: =IF($B22="","",TEXT($B22,"ddd"))
C23: =IF($B23="","",TEXT($B23,"ddd"))
... C44: =IF($B44="","",TEXT($B44,"ddd"))

Sheet Unit_Converter
B2: Maund - Kilogram Converter
B4: 1 maund = 37.32 kilograms (official conversion used throughout this study)
B6: Maunds -> kilograms
B7: Type maund value here | C7: 1
B8: Result - kilograms | C8: =IF(ISNUMBER($C$7),$C$7*37.32,"")
B10: Kilograms -> maunds
B11: Type kg value here | C11: 37.32
B12: Result - maunds | C12: =IF(ISNUMBER($C$11),ROUND($C$11/37.32,4),"")
B14: Reminder - price flags
B15: K | C15: Species not handled by the respondent today.
B16: D | C16: Price declined - keep the row, the flag itself is information.
B17: 0 / '-' | C17: True zero / not applicable. Empty cells are not allowed in species grids.
B18: Conversion | C18: Blue BDT_per_kg columns convert maund quotes automatically - never type over them.

Sheet Codebook_Species
B2: Species Codebook (Methodology Table 3.4)
B4: Code | C4: Local_name | D4: English_common_name | E4: Scientific_name | F4: Price_tier
B5: S01 | C5: Ilish | D5: Hilsa shad | E5: Tenualosa ilisha | F5: High
B6: S02 | C6: Rupchanda | D6: Silver pomfret | E6: Pampus argenteus | F6: High
B7: S03 | C7: Lakkha | D7: Indian salmon (four-finger threadfin) | E7: Eleutheronema tetradactylum | F7: High
B8: S04 | C8: Koral/Kurl | D8: Asian sea bass | E8: Lates calcarifer | F8: High
B9: S05 | C9: Surma | D9: Indian mackerel | E9: Rastrelliger kanagurta | F9: Medium
B10: S06 | C10: Churi | D10: Largehead ribbonfish | E10: Trichiurus lepturus | F10: Medium
B11: S07 | C11: Poa | D11: Pama croaker | E11: Otolithoides pama | F11: Medium
B12: S08 | C12: Kankoita | D12: Thorny/Indian anchovy | E12: Stolephorus indicus | F12: Low-volume
B13: S09 | C13: Loitta | D13: Bombay duck | E13: Harpadon nehereus | F13: Low
B14: S10 | C14: Harina | D14: Chacunda gizzard shad | E14: Anodontostoma chacunda | F14: Low

Sheet Codebook_Markets
B2: Market Codebook (Methodology Table 3.1)
B4: Code | C4: Market_name | D4: Channel_position | E4: Primary_analytical_contribution
B5: M1 | C5: Fishery Ghat | D5: Landing-linked wholesale-cum-retail | E5: First-sale (producer-side) price observations
B6: M2 | C6: Chawkbazar | D6: Retail | E6: Retail prices and trade volume quotes
B7: M3 | C7: Kazir Dewri | D7: Retail | E7: Retail prices and vendor practices
B8: M4 | C8: Karnaphuli Complex | D8: Retail | E8: Retail prices; comparability with the 2019 baseline
B9: M5 | C9: Bahaddarhat | D9: Retail | E9: Newer-generation retail turnover
B10: M6 | C10: Patenga | D10: Landing-linked retail | E10: Coast-side buy prices supporting producer-share estimation

Sheet Form_A_Aratdar
B2: Form A - Aratdar Questionnaire (one respondent per row)
B4: Respondent_ID | C4: Market | D4: Interview_Date | E4: Age_years | F4: Education | G4: Years_in_business | H4: Daily_capacity_raw | I4: Daily_capacity_unit | J4: Daily_capacity_kg | K4: Family_members | L4: Rent_pay_or_receive | M4: Rent_amount_BDT | N4: Rent_frequency | O4: Commission_basis | P4: Commission_rate | Q4: Electricity_bill_BDT | R4: Electricity_frequency | S4: Workers_count | T4: Worker_daily_wage_BDT | U4: Equipment_Cooler_Maintenance_BDT | V4: Equipment_Cooler_Maintenance_frequency | W4: Other_cost_description | X4: Other_cost_BDT | Y4: Payment_cash_pct | Z4: Payment_MFS_pct | AA4: Payment_credit_pct | AB4: MFS_transaction_frequency | AC4: Problem_1 | AD4: Problem_2 | AE4: Problem_3 | AF4: Pair_ID | AG4: Notes
B5: M1-A-01 | C5: M1 | D5: 46084 | E5: 50 | F5: Secondary | G5: 12 | H5: 18 | I5: Maund | J5: 671.76 | K5: 4 | L5: Pay | M5: 30000 | N5: Monthly | O5: Percent | P5: 3 | Q5: 11400 | R5: Monthly | S5: 8 | T5: 600 | U5: 5000 | V5: Monthly | W5: Auction hall cleaning fee | X5: 1100 | Y5: 67 | Z5: 22 | AA5: 11 | AB5: Occasional | AC5: Low landings in lean season | AD5: Unsold fish spoilage loss | AE5: Supply syndicate control | AF5: PAIR-M1-02
B6: M1-A-02 | C6: M1 | D6: 46084 | E6: 32 | F6: Secondary | G6: 16 | H6: 19 | I6: Maund | J6: 709.08 | K6: 3 | L6: Pay | M6: 420000 | N6: Yearly | O6: Kg | P6: 1 | Q6: 8700 | R6: Monthly | S6: 7 | T6: 550 | U6: 7500 | V6: Monthly | W6: Auction hall cleaning fee | X6: 1150 | Y6: 65 | Z6: 10 | AA6: 25 | AB6: Regular | AC6: Rising cost of ice and salt | AD6: Delayed credit recovery | AE6: Competition from frozen imported fish
B7: M1-A-03 | C7: M1 | D7: 46084 | E7: 55 | F7: Secondary | G7: 32 | H7: 14 | I7: Maund | J7: 522.48 | K7: 4 | L7: Pay | M7: 420000 | N7: Yearly | O7: Lot | P7: 1000 | Q7: 12700 | R7: Monthly | S7: 3 | T7: 800 | U7: 12000 | V7: Yearly | W7: Weighing scale repair | X7: 950 | Y7: 80 | Z7: 8 | AA7: 12 | AB7: Regular | AC7: Competition from frozen imported fish | AD7: Day-to-day price volatility | AE7: Transport cost increase
B8: M1-A-04 | C8: M1 | D8: 46084 | E8: 39 | F8: Secondary | G8: 17 | H8: 11 | I8: Maund | J8: 410.52 | K8: 5 | L8: Pay | M8: 240000 | N8: Yearly | O8: Percent | P8: 2 | Q8: 5800 | R8: Monthly | S8: 5 | T8: 700 | U8: 6500 | V8: Yearly | W8: Auction hall cleaning fee | X8: 450 | Y8: 69 | Z8: 20 | AA8: 11 | AB8: Occasional | AC8: Delayed credit recovery | AD8: Supply syndicate control | AE8: Low landings in lean season
B9: M1-A-05 | C9: M1 | D9: 46084 | E9: 57 | F9: Primary | G9: 31 | H9: 29 | I9: Maund | J9: 1082.28 | K9: 9 | L9: Pay | M9: 380000 | N9: Yearly | O9: Percent | P9: 3 | Q9: 12000 | R9: Monthly | S9: 8 | T9: 500 | U9: 9500 | V9: Yearly | W9: Market committee toll | X9: 2000 | Y9: 65 | Z9: 13 | AA9: 22 | AB9: Occasional | AC9: Day-to-day price volatility | AD9: Competition from frozen imported fish | AE9: Rising cost of ice and salt | AF9: PAIR-M1-01
B10: M1-A-06 | C10: M1
B11: M2-A-01 | C11: M2 | D11: 46085 | E11: 29 | F11: Secondary | G11: 13 | H11: 26 | I11: Maund | J11: 970.32 | K11: 3 | L11: Receive | M11: 2000 | N11: Monthly | O11: Percent | P11: 3.5 | Q11: 11100 | R11: Monthly | S11: 6 | T11: 800 | U11: 9000 | V11: Yearly | W11: Weighing scale repair | X11: 500 | Y11: 77 | Z11: 16 | AA11: 7 | AB11: Regular | AC11: Low landings in lean season | AD11: High ice price | AE11: Irregular electricity and load-shedding | AF11: PAIR-M2-02
B12: M2-A-02 | C12: M2 | D12: 46085 | E12: 52 | F12: Illiterate | G12: 20 | H12: 32 | I12: Maund | J12: 1194.24 | K12: 8 | L12: Receive | M12: 2500 | N12: Monthly | O12: Kg | P12: 3 | Q12: 4400 | R12: Monthly | S12: 6 | T12: 650 | U12: 11000 | V12: Yearly | W12: Ice block purchase | X12: 1800 | Y12: 73 | Z12: 7 | AA12: 20 | AB12: Regular | AC12: Competition from frozen imported fish | AD12: Low landings in lean season | AE12: Rising toll and lease burden
B13: M2-A-03 | C13: M2 | D13: 46085 | E13: 34 | F13: Primary | G13: 12 | H13: 10 | I13: Maund | J13: 373.2 | K13: 7 | L13: Pay | M13: 80000 | N13: Yearly | O13: Lot | P13: 500 | Q13: 5300 | R13: Monthly | S13: 6 | T13: 500 | U13: 11000 | V13: Yearly | W13: Ice block purchase | X13: 1300 | Y13: 66 | Z13: 16 | AA13: 18 | AB13: Regular | AC13: Waterlogging during monsoon | AD13: Rising toll and lease burden | AE13: Rising cost of ice and salt
B14: M2-A-04 | C14: M2 | D14: 46085 | E14: 59 | F14: Higher_Secondary | G14: 34 | H14: 21 | I14: Maund | J14: 783.72 | K14: 9 | L14: Pay | M14: 150000 | N14: Yearly | O14: Kg | P14: 3 | Q14: 5000 | R14: Monthly | S14: 3 | T14: 800 | U14: 9000 | V14: Monthly | W14: Weighing scale repair | X14: 1350 | Y14: 61 | Z14: 24 | AA14: 15 | AB14: Never | AC14: Unsold fish spoilage loss | AD14: Waterlogging during monsoon | AE14: High ice price | AF14: PAIR-M2-01
B15: M2-A-05 | C15: M2 | D15: 46085 | E15: 31 | F15: Primary | G15: 11 | H15: 8 | I15: Maund | J15: 298.56 | K15: 5 | L15: Pay | M15: 21000 | N15: Monthly | O15: Percent | P15: 2.5 | Q15: 3100 | R15: Monthly | S15: 6 | T15: 650 | U15: 7500 | V15: Monthly | W15: Union levy | X15: 2300 | Y15: 80 | Z15: 15 | AA15: 5 | AB15: Regular | AC15: Day-to-day price volatility | AD15: Competition from frozen imported fish | AE15: Supply syndicate control | AF15: PAIR-M2-03
B16: M2-A-06 | C16: M2
B17: M3-A-01 | C17: M3 | D17: 46086 | E17: 51 | F17: Secondary | G17: 18 | H17: 21 | I17: Maund | J17: 783.72 | K17: 3 | L17: Pay | M17: 175000 | N17: Yearly | O17: Percent | P17: 2.5 | Q17: 9700 | R17: Monthly | S17: 9 | T17: 600 | U17: 7500 | V17: Monthly | W17: Union levy | X17: 1100 | Y17: 77 | Z17: 14 | AA17: 9 | AB17: Occasional | AC17: High ice price | AD17: Low landings in lean season | AE17: Waterlogging during monsoon
B18: M3-A-02 | C18: M3 | D18: 46086 | E18: 41 | F18: Secondary | G18: 25 | H18: 31 | I18: Maund | J18: 1156.92 | K18: 4 | L18: Pay | M18: 9000 | N18: Monthly | O18: Percent | P18: 2 | Q18: 7600 | R18: Yearly | S18: 4 | T18: 800 | U18: 8500 | V18: Yearly | W18: Union levy | X18: 1350 | Y18: 76 | Z18: 5 | AA18: 19 | AB18: Regular | AC18: Competition from frozen imported fish | AD18: Waterlogging during monsoon | AE18: Transport cost increase | AF18: PAIR-M3-01
B19: M3-A-03 | C19: M3 | D19: 46086 | E19: 58 | F19: Primary | G19: 30 | H19: 29 | I19: Maund | J19: 1082.28 | K19: 7 | L19: Pay | M19: 165000 | N19: Yearly | O19: Kg | P19: 1.5 | Q19: 3200 | R19: Monthly | S19: 6 | T19: 550 | U19: 6500 | V19: Yearly | W19: Auction hall cleaning fee | X19: 950 | Y19: 68 | Z19: 16 | AA19: 16 | AB19: Occasional | AC19: Rising cost of ice and salt | AD19: Low landings in lean season | AE19: Waterlogging during monsoon
B20: M3-A-04 | C20: M3 | D20: 46086 | E20: 48 | F20: Primary | G20: 8 | H20: 20 | I20: Maund | J20: 746.4 | K20: 3 | L20: Pay | M20: 75000 | N20: Yearly | O20: Percent | P20: 2 | Q20: 7300 | R20: Monthly | S20: 6 | T20: 550 | U20: 4000 | V20: Yearly | W20: Ice block purchase | X20: 1950 | Y20: 78 | Z20: 5 | AA20: 17 | AB20: Occasional | AC20: Rising cost of ice and salt | AD20: Day-to-day price volatility | AE20: Delayed credit recovery
B21: M3-A-05 | C21: M3 | D21: 46086 | E21: 46 | F21: Secondary | G21: 30 | H21: 26 | I21: Maund | J21: 970.32 | K21: 5 | L21: Receive | M21: 3500 | N21: Monthly | O21: Percent | P21: 2 | Q21: 11700 | R21: Monthly | S21: 3 | T21: 650 | U21: 2500 | V21: Yearly | W21: Weighing scale repair | X21: 800 | Y21: 73 | Z21: 7 | AA21: 20 | AB21: Occasional | AC21: High ice price | AD21: Low landings in lean season | AE21: Irregular electricity and load-shedding | AF21: PAIR-M3-02
B22: M3-A-06 | C22: M3
B23: M4-A-01 | C23: M4 | D23: 46087 | E23: 52 | F23: Primary | G23: 23 | H23: 28 | I23: Maund | J23: 1044.96 | K23: 8 | L23: Pay | M23: 17000 | N23: Monthly | O23: Percent | P23: 3.5 | Q23: 7100 | R23: Monthly | S23: 7 | T23: 550 | U23: 4000 | V23: Yearly | W23: Weighing scale repair | X23: 550 | Y23: 62 | Z23: 6 | AA23: 32 | AB23: Never | AC23: Unsold fish spoilage loss | AD23: Waterlogging during monsoon | AE23: Low landings in lean season | AF23: PAIR-M4-01
B24: M4-A-02 | C24: M4 | D24: 46087 | E24: 57 | F24: Secondary | G24: 24 | H24: 32 | I24: Maund | J24: 1194.24 | K24: 8 | L24: Pay | M24: 100000 | N24: Yearly | O24: Percent | P24: 4 | Q24: 11800 | R24: Monthly | S24: 5 | T24: 750 | U24: 9500 | V24: Monthly | W24: Auction hall cleaning fee | X24: 350 | Y24: 66 | Z24: 20 | AA24: 14 | AB24: Regular | AC24: Competition from frozen imported fish | AD24: Unsold fish spoilage loss | AE24: Delayed credit recovery | AF24: PAIR-M4-03
B25: M4-A-03 | C25: M4 | D25: 46087 | E25: 37 | F25: Secondary | G25: 21 | H25: 9 | I25: Maund | J25: 335.88 | K25: 8 | L25: Pay | M25: 110000 | N25: Yearly | O25: Percent | P25: 3.5 | Q25: 7200 | R25: Monthly | S25: 2 | T25: 650 | U25: 10000 | V25: Monthly | W25: Weighing scale repair | X25: 650 | Y25: 76 | Z25: 18 | AA25: 6 | AB25: Regular | AC25: Rising toll and lease burden | AD25: Rising cost of ice and salt | AE25: Unsold fish spoilage loss | AF25: PAIR-M4-02
B26: M4-A-04 | C26: M4 | D26: 46087 | E26: 40 | F26: Primary | G26: 5 | H26: 26 | I26: Maund | J26: 970.32 | K26: 7 | L26: Pay | M26: 175000 | N26: Yearly | O26: Percent | P26: 4 | Q26: 6500 | R26: Monthly | S26: 8 | T26: 650 | U26: 3500 | V26: Yearly | W26: Union levy | X26: 1300 | Y26: 67 | Z26: 9 | AA26: 24 | AB26: Occasional | AC26: Rising cost of ice and salt | AD26: Delayed credit recovery | AE26: Transport cost increase
B27: M4-A-05 | C27: M4 | D27: 46087 | E27: 62 | F27: Higher_Secondary | G27: 27 | H27: 24 | I27: Maund | J27: 895.68 | K27: 5 | L27: Pay | M27: 120000 | N27: Yearly | O27: Lot | P27: 2000 | Q27: 4400 | R27: Monthly | S27: 3 | T27: 700 | U27: 8000 | V27: Yearly | W27: Weighing scale repair | X27: 800 | Y27: 67 | Z27: 18 | AA27: 15 | AB27: Regular | AC27: Waterlogging during monsoon | AD27: Irregular electricity and load-shedding | AE27: Competition from frozen imported fish
B28: M4-A-06 | C28: M4
B29: M5-A-01 | C29: M5 | D29: 46088 | E29: 58 | F29: Illiterate | G29: 20 | H29: 29 | I29: Maund | J29: 1082.28 | K29: 4 | L29: Pay | M29: 190000 | N29: Yearly | O29: Percent | P29: 2.5 | Q29: 2900 | R29: Monthly | S29: 2 | T29: 700 | U29: 10500 | V29: Yearly | W29: Market committee toll | X29: 1050 | Y29: 56 | Z29: 25 | AA29: 19 | AB29: Occasional | AC29: Day-to-day price volatility | AD29: Unsold fish spoilage loss | AE29: Waterlogging during monsoon | AF29: PAIR-M5-03
B30: M5-A-02 | C30: M5 | D30: 46088 | E30: 44 | F30: Primary | G30: 28 | H30: 9 | I30: Maund | J30: 335.88 | K30: 7 | L30: Pay | M30: 10000 | N30: Monthly | O30: Lot | P30: 2000 | Q30: 8200 | R30: Monthly | S30: 3 | T30: 650 | U30: 8500 | V30: Yearly | W30: Weighing scale repair | X30: 1250 | Y30: 71 | Z30: 20 | AA30: 9 | AB30: Occasional | AC30: Supply syndicate control | AD30: Competition from frozen imported fish | AE30: Day-to-day price volatility | AF30: PAIR-M5-02
B31: M5-A-03 | C31: M5 | D31: 46088 | E31: 38 | F31: Primary | G31: 22 | H31: 12 | I31: Maund | J31: 447.84 | K31: 9 | L31: Receive | M31: 4000 | N31: Monthly | O31: Percent | P31: 3 | Q31: 10500 | R31: Monthly | S31: 3 | T31: 700 | U31: 2000 | V31: Yearly | W31: Ice block purchase | X31: 2250 | Y31: 73 | Z31: 15 | AA31: 12 | AB31: Regular | AC31: Delayed credit recovery | AD31: High ice price | AE31: Unsold fish spoilage loss | AF31: PAIR-M5-01
B32: M5-A-04 | C32: M5 | D32: 46088 | E32: 40 | F32: Secondary | G32: 24 | H32: 33 | I32: Maund | J32: 1231.56 | K32: 8 | L32: Receive | M32: 2000 | N32: Monthly | O32: Percent | P32: 2.5 | Q32: 13100 | R32: Monthly | S32: 3 | T32: 800 | U32: 3000 | V32: Yearly | W32: Auction hall cleaning fee | X32: 650 | Y32: 64 | Z32: 20 | AA32: 16 | AB32: Occasional | AC32: Waterlogging during monsoon | AD32: Competition from frozen imported fish | AE32: Irregular electricity and load-shedding
B33: M5-A-05 | C33: M5 | D33: 46088 | E33: 50 | F33: Primary | G33: 10 | H33: 11 | I33: Maund | J33: 410.52 | K33: 5 | L33: Pay | M33: 130000 | N33: Yearly | O33: Percent | P33: 5 | Q33: 2700 | R33: Monthly | S33: 9 | T33: 700 | U33: 8500 | V33: Monthly | W33: Weighing scale repair | X33: 650 | Y33: 69 | Z33: 18 | AA33: 13 | AB33: Regular | AC33: Transport cost increase | AD33: Supply syndicate control | AE33: High ice price
B34: M5-A-06 | C34: M5
B35: M6-A-01 | C35: M6 | D35: 46084 | E35: 41 | F35: Secondary | G35: 22 | H35: 33 | I35: Maund | J35: 1231.56 | K35: 3 | L35: Pay | M35: 175000 | N35: Yearly | O35: Lot | P35: 2500 | Q35: 6000 | R35: Monthly | S35: 3 | T35: 800 | U35: 1500 | V35: Yearly | W35: Union levy | X35: 1700 | Y35: 80 | Z35: 12 | AA35: 8 | AB35: Occasional | AC35: Unsold fish spoilage loss | AD35: Delayed credit recovery | AE35: High ice price
B36: M6-A-02 | C36: M6 | D36: 46084 | E36: 59 | F36: Secondary | G36: 40 | H36: 26 | I36: Maund | J36: 970.32 | K36: 8 | L36: Pay | M36: 140000 | N36: Yearly | O36: Lot | P36: 500 | Q36: 9700 | R36: Monthly | S36: 7 | T36: 750 | U36: 8000 | V36: Monthly | W36: Market committee toll | X36: 2500 | Y36: 79 | Z36: 14 | AA36: 7 | AB36: Never | AC36: High ice price | AD36: Supply syndicate control | AE36: Rising toll and lease burden | AF36: PAIR-M6-01
B37: M6-A-03 | C37: M6 | D37: 46084 | E37: 46 | F37: Illiterate | G37: 5 | H37: 12 | I37: Maund | J37: 447.84 | K37: 3 | L37: Pay | M37: 19000 | N37: Monthly | O37: Percent | P37: 3.5 | Q37: 9900 | R37: Monthly | S37: 8 | T37: 750 | U37: 4000 | V37: Monthly | W37: Union levy | X37: 600 | Y37: 55 | Z37: 6 | AA37: 39 | AB37: Regular | AC37: Waterlogging during monsoon | AD37: Rising cost of ice and salt | AE37: Unsold fish spoilage loss
B38: M6-A-04 | C38: M6 | D38: 46084 | E38: 57 | F38: Primary | G38: 30 | H38: 34 | I38: Maund | J38: 1268.88 | K38: 7 | L38: Pay | M38: 125000 | N38: Yearly | O38: Percent | P38: 2.5 | Q38: 12200 | R38: Monthly | S38: 6 | T38: 650 | U38: 6000 | V38: Yearly | W38: Auction hall cleaning fee | X38: 800 | Y38: 66 | Z38: 12 | AA38: 22 | AB38: Regular | AC38: Delayed credit recovery | AD38: Day-to-day price volatility | AE38: Low landings in lean season
B39: M6-A-05 | C39: M6 | D39: 46084 | E39: 50 | F39: Illiterate | G39: 9 | H39: 11 | I39: Maund | J39: 410.52 | K39: 8 | L39: Receive | M39: 3500 | N39: Monthly | O39: Percent | P39: 2 | Q39: 6600 | R39: Monthly | S39: 9 | T39: 700 | U39: 6500 | V39: Yearly | W39: Ice block purchase | X39: 2700 | Y39: 63 | Z39: 14 | AA39: 23 | AB39: Never | AC39: Rising toll and lease burden | AD39: High ice price | AE39: Competition from frozen imported fish | AF39: PAIR-M6-02
B40: M6-A-06 | C40: M6

Sheet Form_B_Bepari_Faria
B2: Form B - Bepari/Faria Questionnaire (one respondent per row)
B4: Respondent_ID | C4: Market | D4: Interview_Date | E4: Actor_subtype | F4: Business_pattern | G4: Age_years | H4: Education | I4: Years_in_business | J4: Daily_capacity_raw | K4: Daily_capacity_unit | L4: Daily_capacity_kg | M4: Family_members | N4: Source_location | O4: Supplier_category | P4: Transport_fare_per_trip_BDT | Q4: Trip_frequency_days | R4: Trips_per_period | S4: Loading_Unloading_cost_per_trip_BDT | T4: Ice_usage_kg_per_day | U4: Ice_cost_BDT_per_day | V4: Commission_to_aratdar_value | W4: Commission_unit | X4: Transit_damage_pct | Y4: Payment_cash_pct | Z4: Payment_MFS_pct | AA4: Payment_credit_pct | AB4: MFS_transaction_frequency | AC4: Credit_sales_share | AD4: Problem_1 | AE4: Problem_2 | AF4: Problem_3 | AG4: Pair_ID | AH4: Notes
B5: M1-B-01 | C5: M1 | D5: 46084 | E5: Bepari | F5: Seasonal | G5: 43 | H5: Primary | I5: 27 | J5: 5 | K5: Maund | L5: 186.6 | M5: 7 | N5: Fishery Ghat landing | O5: Faria | P5: 1750 | Q5: 2 | R5: 1 | S5: 250 | T5: 44 | U5: 170 | V5: 3 | W5: Percent_of_lot | X5: 4 | Y5: 55 | Z5: 15 | AA5: 30 | AB5: Regular | AC5: Some | AD5: High ice price | AE5: Low landings in lean season | AF5: Rising toll and lease burden
B6: M1-B-02 | C6: M1 | D6: 46084 | E6: Bepari | F6: Seasonal | G6: 25 | H6: Secondary | I6: 9 | J6: 7 | K6: Maund | L6: 261.24 | M6: 6 | N6: Karnaphuli river ghat | O6: Other | P6: 450 | Q6: 2 | R6: 1 | S6: 500 | T6: 35 | U6: 130 | V6: 4 | W6: Percent_of_lot | X6: 7 | Y6: 55 | Z6: 30 | AA6: 15 | AB6: Regular | AC6: None | AD6: Day-to-day price volatility | AE6: Rising cost of ice and salt | AF6: Rising toll and lease burden
B7: M1-B-03 | C7: M1 | D7: 46084 | E7: Bepari | F7: Seasonal | G7: 27 | H7: Illiterate | I7: 11 | J7: 5 | K7: Maund | L7: 186.6 | M7: 7 | N7: Fishery Ghat landing | O7: Aratdar | P7: 900 | Q7: 3 | R7: 1 | S7: 150 | T7: 109 | U7: 300 | V7: 3 | W7: Percent_of_lot | X7: 5 | Y7: 67 | Z7: 27 | AA7: 6 | AB7: Never | AC7: Some | AD7: Rising cost of ice and salt | AE7: Low landings in lean season | AF7: Waterlogging during monsoon
B8: M1-B-04 | C8: M1 | D8: 46084 | E8: Bepari | F8: Seasonal | G8: 51 | H8: Secondary | I8: 5 | J8: 4 | K8: Maund | L8: 149.28 | M8: 7 | N8: Karnaphuli river ghat | O8: Aratdar | P8: 500 | Q8: 2 | R8: 3 | S8: 100 | T8: 32 | U8: 80 | V8: 4 | W8: Percent_of_lot | X8: 8 | Y8: 79 | Z8: 10 | AA8: 11 | AB8: Occasional | AC8: None | AD8: Rising toll and lease burden | AE8: Day-to-day price volatility | AF8: Waterlogging during monsoon
B9: M1-B-05 | C9: M1 | D9: 46084 | E9: Bepari | F9: Year_round | G9: 40 | H9: Secondary | I9: 18 | J9: 4 | K9: Maund | L9: 149.28 | M9: 3 | N9: Karnaphuli river ghat | O9: Aratdar | P9: 2650 | Q9: 3 | R9: 1 | S9: 100 | T9: 99 | U9: 390 | V9: 800 | W9: BDT_per_lot | X9: 8 | Y9: 54 | Z9: 28 | AA9: 18 | AB9: Occasional | AC9: Some | AD9: Supply syndicate control | AE9: High ice price | AF9: Low landings in lean season
B10: M1-B-06 | C10: M1
B11: M2-B-01 | C11: M2 | D11: 46085 | E11: Bepari | F11: Year_round | G11: 45 | H11: Primary | I11: 12 | J11: 4 | K11: Maund | L11: 149.28 | M11: 4 | N11: Kuakata | O11: Fisherman | P11: 1650 | Q11: 1 | R11: 2 | S11: 250 | T11: 65 | U11: 180 | V11: 4 | W11: Percent_of_lot | X11: 6 | Y11: 62 | Z11: 15 | AA11: 23 | AB11: Regular | AC11: Some | AD11: Irregular electricity and load-shedding | AE11: Supply syndicate control | AF11: Unsold fish spoilage loss
B12: M2-B-02 | C12: M2 | D12: 46085 | E12: Bepari | F12: Year_round | G12: 46 | H12: Secondary | I12: 25 | J12: 6 | K12: Maund | L12: 223.92 | M12: 8 | N12: Teknaf | O12: Fisherman | P12: 2400 | Q12: 3 | R12: 3 | S12: 150 | T12: 110 | U12: 310 | V12: 3 | W12: Percent_of_lot | X12: 8 | Y12: 60 | Z12: 7 | AA12: 33 | AB12: Regular | AC12: Some | AD12: Delayed credit recovery | AE12: Rising toll and lease burden | AF12: Rising cost of ice and salt
B13: M2-B-03 | C13: M2 | D13: 46085 | E13: Bepari | F13: Year_round | G13: 51 | H13: Secondary | I13: 9 | J13: 9 | K13: Maund | L13: 335.88 | M13: 4 | N13: Karnaphuli river ghat | O13: Fisherman | P13: 3250 | Q13: 2 | R13: 2 | S13: 100 | T13: 88 | U13: 220 | V13: 4 | W13: Percent_of_lot | X13: 3 | Y13: 56 | Z13: 23 | AA13: 21 | AB13: Occasional | AC13: None | AD13: Supply syndicate control | AE13: Delayed credit recovery | AF13: Irregular electricity and load-shedding
B14: M2-B-04 | C14: M2 | D14: 46085 | E14: Bepari | F14: Year_round | G14: 27 | H14: Secondary | I14: 11 | J14: 8 | K14: Maund | L14: 298.56 | M14: 2 | N14: Kuakata | O14: Aratdar | P14: 2300 | Q14: 2 | R14: 2 | S14: 450 | T14: 68 | U14: 260 | V14: 3.5 | W14: Percent_of_lot | X14: 5 | Y14: 68 | Z14: 8 | AA14: 24 | AB14: Occasional | AC14: None | AD14: Day-to-day price volatility | AE14: Transport cost increase | AF14: Waterlogging during monsoon
B15: M2-B-05 | C15: M2 | D15: 46085 | E15: Bepari | F15: Year_round | G15: 58 | H15: Primary | I15: 5 | J15: 8 | K15: Maund | L15: 298.56 | M15: 4 | N15: Fishery Ghat landing | O15: Fisherman | P15: 2750 | Q15: 3 | R15: 1 | S15: 100 | T15: 57 | U15: 190 | V15: 2 | W15: Percent_of_lot | X15: 4 | Y15: 72 | Z15: 18 | AA15: 10 | AB15: Never | AC15: Some | AD15: Transport cost increase | AE15: Irregular electricity and load-shedding | AF15: Day-to-day price volatility
B16: M2-B-06 | C16: M2
B17: M3-B-01 | C17: M3 | D17: 46086 | E17: Bepari | F17: Year_round | G17: 34 | H17: Primary | I17: 18 | J17: 4 | K17: Maund | L17: 149.28 | M17: 2 | N17: Moheshkhali | O17: Faria | P17: 3200 | Q17: 3 | R17: 1 | S17: 100 | T17: 66 | U17: 220 | V17: 4 | W17: Percent_of_lot | X17: 5 | Y17: 54 | Z17: 21 | AA17: 25 | AB17: Occasional | AC17: Some | AD17: Low landings in lean season | AE17: Rising cost of ice and salt | AF17: Irregular electricity and load-shedding
B18: M3-B-02 | C18: M3 | D18: 46086 | E18: Faria | F18: Seasonal | G18: 43 | H18: Secondary | I18: 27 | J18: 3.9 | K18: Maund | L18: 145.55 | M18: 5 | N18: Kutubdia | O18: Fisherman | P18: 800 | Q18: 1 | R18: 3 | S18: 150 | T18: 64 | U18: 250 | V18: 1500 | W18: BDT_per_lot | X18: 2 | Y18: 77 | Z18: 10 | AA18: 13 | AB18: Occasional | AC18: Some | AD18: Transport cost increase | AE18: Rising cost of ice and salt | AF18: Low landings in lean season
B19: M3-B-03 | C19: M3 | D19: 46086 | E19: Bepari | F19: Seasonal | G19: 29 | H19: Secondary | I19: 13 | J19: 5 | K19: Maund | L19: 186.6 | M19: 3 | N19: Teknaf | O19: Fisherman | P19: 1750 | Q19: 1 | R19: 2 | S19: 450 | T19: 79 | U19: 220 | V19: 2 | W19: Percent_of_lot | X19: 2 | Y19: 76 | Z19: 15 | AA19: 9 | AB19: Regular | AC19: Some | AD19: Competition from frozen imported fish | AE19: High ice price | AF19: Delayed credit recovery
B20: M3-B-04 | C20: M3 | D20: 46086 | E20: Bepari | F20: Year_round | G20: 41 | H20: Primary | I20: 25 | J20: 4 | K20: Maund | L20: 149.28 | M20: 6 | N20: Bhola charter landing | O20: Faria | P20: 1950 | Q20: 3 | R20: 3 | S20: 500 | T20: 120 | U20: 470 | V20: 2.5 | W20: Percent_of_lot | X20: 7 | Y20: 79 | Z20: 5 | AA20: 16 | AB20: Regular | AC20: Some | AD20: Waterlogging during monsoon | AE20: Transport cost increase | AF20: Rising cost of ice and salt
B21: M3-B-05 | C21: M3 | D21: 46086 | E21: Bepari | F21: Year_round | G21: 30 | H21: Higher_Secondary | I21: 14 | J21: 4 | K21: Maund | L21: 149.28 | M21: 3 | N21: Teknaf | O21: Fisherman | P21: 3500 | Q21: 1 | R21: 2 | S21: 200 | T21: 38 | U21: 140 | V21: 3.5 | W21: Percent_of_lot | X21: 4 | Y21: 54 | Z21: 23 | AA21: 23 | AB21: Never | AC21: None | AD21: Rising cost of ice and salt | AE21: Day-to-day price volatility | AF21: Low landings in lean season
B22: M3-B-06 | C22: M3
B23: M4-B-01 | C23: M4 | D23: 46087 | E23: Bepari | F23: Year_round | G23: 54 | H23: Illiterate | I23: 33 | J23: 7 | K23: Maund | L23: 261.24 | M23: 4 | N23: Bhola charter landing | O23: Aratdar | P23: 800 | Q23: 1 | R23: 1 | S23: 500 | T23: 93 | U23: 260 | V23: 2 | W23: Percent_of_lot | X23: 7 | Y23: 51 | Z23: 16 | AA23: 33 | AB23: Occasional | AC23: Some | AD23: Irregular electricity and load-shedding | AE23: Day-to-day price volatility | AF23: High ice price
B24: M4-B-02 | C24: M4 | D24: 46087 | E24: Faria | F24: Year_round | G24: 50 | H24: Primary | I24: 17 | J24: 3.2 | K24: Maund | L24: 119.42 | M24: 8 | N24: Bhola charter landing | O24: Aratdar | P24: 3050 | Q24: 1 | R24: 3 | S24: 350 | T24: 74 | U24: 190 | V24: 2 | W24: Percent_of_lot | X24: 3 | Y24: 62 | Z24: 29 | AA24: 9 | AB24: Occasional | AC24: None | AD24: Rising toll and lease burden | AE24: Delayed credit recovery | AF24: Day-to-day price volatility
B25: M4-B-03 | C25: M4 | D25: 46087 | E25: Faria | F25: Seasonal | G25: 29 | H25: Primary | I25: 13 | J25: 3.6 | K25: Maund | L25: 134.35 | M25: 2 | N25: Bhola charter landing | O25: Aratdar | P25: 2600 | Q25: 1 | R25: 3 | S25: 450 | T25: 101 | U25: 400 | V25: 800 | W25: BDT_per_lot | X25: 6 | Y25: 70 | Z25: 10 | AA25: 20 | AB25: Occasional | AC25: Some | AD25: Rising cost of ice and salt | AE25: Waterlogging during monsoon | AF25: Rising toll and lease burden
B26: M4-B-04 | C26: M4 | D26: 46087 | E26: Bepari | F26: Year_round | G26: 44 | H26: Higher_Secondary | I26: 18 | J26: 9 | K26: Maund | L26: 335.88 | M26: 3 | N26: Moheshkhali | O26: Fisherman | P26: 1650 | Q26: 2 | R26: 1 | S26: 500 | T26: 55 | U26: 150 | V26: 2 | W26: Percent_of_lot | X26: 6 | Y26: 54 | Z26: 30 | AA26: 16 | AB26: Occasional | AC26: Some | AD26: Day-to-day price volatility | AE26: Irregular electricity and load-shedding | AF26: Transport cost increase
B27: M4-B-05 | C27: M4 | D27: 46087 | E27: Bepari | F27: Year_round | G27: 23 | H27: Primary | I27: 5 | J27: 8 | K27: Maund | L27: 298.56 | M27: 6 | N27: Kuakata | O27: Fisherman | P27: 1600 | Q27: 3 | R27: 3 | S27: 200 | T27: 115 | U27: 290 | V27: 3 | W27: Percent_of_lot | X27: 6 | Y27: 64 | Z27: 7 | AA27: 29 | AB27: Regular | AC27: Some | AD27: Irregular electricity and load-shedding | AE27: Waterlogging during monsoon | AF27: Low landings in lean season
B28: M4-B-06 | C28: M4
B29: M5-B-01 | C29: M5 | D29: 46088 | E29: Faria | F29: Seasonal | G29: 53 | H29: Primary | I29: 10 | J29: 1.3 | K29: Maund | L29: 48.52 | M29: 4 | N29: Fishery Ghat landing | O29: Aratdar | P29: 3000 | Q29: 3 | R29: 3 | S29: 250 | T29: 31 | U29: 110 | V29: 3 | W29: Percent_of_lot | X29: 6 | Y29: 63 | Z29: 29 | AA29: 8 | AB29: Occasional | AC29: Some | AD29: High ice price | AE29: Competition from frozen imported fish | AF29: Day-to-day price volatility
B30: M5-B-02 | C30: M5 | D30: 46088 | E30: Bepari | F30: Year_round | G30: 57 | H30: Secondary | I30: 35 | J30: 10 | K30: Maund | L30: 373.2 | M30: 3 | N30: Karnaphuli river ghat | O30: Aratdar | P30: 1750 | Q30: 3 | R30: 1 | S30: 150 | T30: 64 | U30: 210 | V30: 300 | W30: BDT_per_lot | X30: 5 | Y30: 56 | Z30: 25 | AA30: 19 | AB30: Occasional | AC30: Some | AD30: Supply syndicate control | AE30: Rising toll and lease burden | AF30: High ice price
B31: M5-B-03 | C31: M5 | D31: 46088 | E31: Bepari | F31: Year_round | G31: 49 | H31: Primary | I31: 28 | J31: 8 | K31: Maund | L31: 298.56 | M31: 6 | N31: Teknaf | O31: Fisherman | P31: 2800 | Q31: 2 | R31: 2 | S31: 350 | T31: 108 | U31: 300 | V31: 500 | W31: BDT_per_lot | X31: 7 | Y31: 72 | Z31: 21 | AA31: 7 | AB31: Regular | AC31: Some | AD31: High ice price | AE31: Waterlogging during monsoon | AF31: Rising cost of ice and salt
B32: M5-B-04 | C32: M5 | D32: 46088 | E32: Faria | F32: Seasonal | G32: 38 | H32: Primary | I32: 22 | J32: 1.9 | K32: Maund | L32: 70.91 | M32: 3 | N32: Moheshkhali | O32: Fisherman | P32: 2550 | Q32: 1 | R32: 1 | S32: 200 | T32: 31 | U32: 110 | V32: 1500 | W32: BDT_per_lot | X32: 3 | Y32: 54 | Z32: 28 | AA32: 18 | AB32: Occasional | AC32: Some | AD32: Rising toll and lease burden | AE32: Waterlogging during monsoon | AF32: Supply syndicate control
B33: M5-B-05 | C33: M5 | D33: 46088 | E33: Bepari | F33: Year_round | G33: 23 | H33: Primary | I33: 7 | J33: 4 | K33: Maund | L33: 149.28 | M33: 5 | N33: Bhola charter landing | O33: Aratdar | P33: 2250 | Q33: 2 | R33: 2 | S33: 250 | T33: 91 | U33: 330 | V33: 4 | W33: Percent_of_lot | X33: 8 | Y33: 59 | Z33: 9 | AA33: 32 | AB33: Occasional | AC33: None | AD33: High ice price | AE33: Low landings in lean season | AF33: Transport cost increase
B34: M5-B-06 | C34: M5
B35: M6-B-01 | C35: M6 | D35: 46084 | E35: Bepari | F35: Year_round | G35: 32 | H35: Illiterate | I35: 16 | J35: 9 | K35: Maund | L35: 335.88 | M35: 8 | N35: Fishery Ghat landing | O35: Faria | P35: 700 | Q35: 3 | R35: 1 | S35: 400 | T35: 33 | U35: 100 | V35: 2 | W35: Percent_of_lot | X35: 5 | Y35: 70 | Z35: 5 | AA35: 25 | AB35: Occasional | AC35: Some | AD35: Rising toll and lease burden | AE35: Supply syndicate control | AF35: Transport cost increase
B36: M6-B-02 | C36: M6 | D36: 46084 | E36: Bepari | F36: Seasonal | G36: 47 | H36: Secondary | I36: 13 | J36: 12 | K36: Maund | L36: 447.84 | M36: 3 | N36: Fishery Ghat landing | O36: Fisherman | P36: 1400 | Q36: 2 | R36: 2 | S36: 450 | T36: 67 | U36: 210 | V36: 3 | W36: Percent_of_lot | X36: 3 | Y36: 80 | Z36: 12 | AA36: 8 | AB36: Regular | AC36: Almost_all | AD36: Irregular electricity and load-shedding | AE36: Delayed credit recovery | AF36: Supply syndicate control
B37: M6-B-03 | C37: M6 | D37: 46084 | E37: Faria | F37: Seasonal | G37: 41 | H37: Secondary | I37: 14 | J37: 1.3 | K37: Maund | L37: 48.52 | M37: 3 | N37: Karnaphuli river ghat | O37: Fisherman | P37: 2550 | Q37: 1 | R37: 2 | S37: 350 | T37: 79 | U37: 210 | V37: 500 | W37: BDT_per_lot | X37: 8 | Y37: 62 | Z37: 25 | AA37: 13 | AB37: Never | AC37: Some | AD37: Day-to-day price volatility | AE37: Irregular electricity and load-shedding | AF37: Supply syndicate control
B38: M6-B-04 | C38: M6 | D38: 46084 | E38: Faria | F38: Year_round | G38: 53 | H38: Secondary | I38: 17 | J38: 1.8 | K38: Maund | L38: 67.18 | M38: 5 | N38: Karnaphuli river ghat | O38: Aratdar | P38: 2050 | Q38: 3 | R38: 3 | S38: 300 | T38: 95 | U38: 310 | V38: 300 | W38: BDT_per_lot | X38: 2 | Y38: 66 | Z38: 6 | AA38: 28 | AB38: Never | AC38: Some | AD38: High ice price | AE38: Transport cost increase | AF38: Unsold fish spoilage loss
B39: M6-B-05 | C39: M6 | D39: 46084 | E39: Faria | F39: Year_round | G39: 56 | H39: Secondary | I39: 11 | J39: 4 | K39: Maund | L39: 149.28 | M39: 7 | N39: Karnaphuli river ghat | O39: Fisherman | P39: 750 | Q39: 1 | R39: 3 | S39: 250 | T39: 96 | U39: 330 | V39: 3.5 | W39: Percent_of_lot | X39: 4 | Y39: 69 | Z39: 16 | AA39: 15 | AB39: Occasional | AC39: Some | AD39: Rising cost of ice and salt | AE39: Waterlogging during monsoon | AF39: Unsold fish spoilage loss
B40: M6-B-06 | C40: M6

Sheet Form_R_Khuchra
B2: Form R - Khuchra (Retail) Vendor Questionnaire (one respondent per row)
B4: Respondent_ID | C4: Market | D4: Interview_Date | E4: Age_years | F4: Education | G4: Years_in_business | H4: Daily_capacity_raw | I4: Daily_capacity_unit | J4: Daily_capacity_kg | K4: Family_members | L4: Shop_Van_Rent_BDT_per_day | M4: Ice_cost_BDT_per_day | N4: Wash_Water_Other_cost_BDT_per_day | O4: Spoilage_pct | P4: Buys_from | Q4: Sells_to | R4: Payment_cash_pct | S4: Payment_MFS_pct | T4: Payment_credit_pct | U4: MFS_transaction_frequency | V4: Sells_on_credit | W4: Problem_1 | X4: Problem_2 | Y4: Problem_3 | Z4: Pair_ID | AA4: Notes
B5: M1-R-01 | C5: M1 | D5: 46084 | E5: 55 | F5: Primary | G5: 6 | H5: 58 | I5: Kg | J5: 58 | K5: 5 | L5: 255 | M5: 185 | N5: 60 | O5: 3 | P5: Aratdar | Q5: Hawker | R5: 47 | S5: 41 | T5: 12 | U5: Occasional | V5: Some | W5: Competition from frozen imported fish | X5: Day-to-day price volatility | Y5: Rising toll and lease burden
B6: M1-R-02 | C6: M1 | D6: 46084 | E6: 31 | F6: Illiterate | G6: 15 | H6: 144 | I6: Kg | J6: 144 | K6: 2 | L6: 190 | M6: 150 | N6: 35 | O6: 4 | P6: Aratdar | Q6: Hawker | R6: 51 | S6: 15 | T6: 34 | U6: Occasional | V6: Some | W6: Transport cost increase | X6: Low landings in lean season | Y6: Supply syndicate control | Z6: PAIR-M1-02
B7: M1-R-03 | C7: M1 | D7: 46084 | E7: 33 | F7: Higher_Secondary | G7: 5 | H7: 43 | I7: Kg | J7: 43 | K7: 3 | L7: 245 | M7: 195 | N7: 105 | O7: 5 | P7: Aratdar | Q7: Household | R7: 69 | S7: 19 | T7: 12 | U7: Occasional | V7: Some | W7: Unsold fish spoilage loss | X7: Low landings in lean season | Y7: Delayed credit recovery
B8: M1-R-04 | C8: M1 | D8: 46084 | E8: 33 | F8: Secondary | G8: 6 | H8: 119 | I8: Kg | J8: 119 | K8: 7 | L8: 320 | M8: 105 | N8: 125 | O8: 8 | P8: Aratdar | Q8: Hotel | R8: 41 | S8: 40 | T8: 19 | U8: Occasional | V8: Almost_all | W8: Low landings in lean season | X8: Supply syndicate control | Y8: Rising toll and lease burden
B9: M1-R-05 | C9: M1 | D9: 46084 | E9: 43 | F9: Primary | G9: 3 | H9: 2.5 | I9: Maund | J9: 93.3 | K9: 7 | L9: 210 | M9: 170 | N9: 115 | O9: 8 | P9: Aratdar | Q9: Household | R9: 52 | S9: 28 | T9: 20 | U9: Occasional | V9: No | W9: Transport cost increase | X9: High ice price | Y9: Day-to-day price volatility | Z9: PAIR-M1-01
B10: M1-R-06 | C10: M1
B11: M2-R-01 | C11: M2 | D11: 46085 | E11: 30 | F11: Illiterate | G11: 4 | H11: 61 | I11: Kg | J11: 61 | K11: 8 | L11: 270 | M11: 230 | N11: 140 | O11: 5 | P11: Faria | Q11: Household | R11: 66 | S11: 27 | T11: 7 | U11: Occasional | V11: Some | W11: Waterlogging during monsoon | X11: Delayed credit recovery | Y11: Transport cost increase | Z11: PAIR-M2-03
B12: M2-R-02 | C12: M2 | D12: 46085 | E12: 40 | F12: Primary | G12: 22 | H12: 2.8 | I12: Maund | J12: 104.5 | K12: 2 | L12: 90 | M12: 205 | N12: 45 | O12: 3 | P12: Aratdar | Q12: Household | R12: 48 | S12: 36 | T12: 16 | U12: Regular | V12: Some | W12: Rising toll and lease burden | X12: Supply syndicate control | Y12: Delayed credit recovery
B13: M2-R-03 | C13: M2 | D13: 46085 | E13: 39 | F13: Primary | G13: 3 | H13: 2.7 | I13: Maund | J13: 100.76 | K13: 3 | L13: 330 | M13: 200 | N13: 70 | O13: 3 | P13: Aratdar | Q13: Institutional | R13: 49 | S13: 20 | T13: 31 | U13: Occasional | V13: Some | W13: Low landings in lean season | X13: Day-to-day price volatility | Y13: Waterlogging during monsoon | Z13: PAIR-M2-01
B14: M2-R-04 | C14: M2 | D14: 46085 | E14: 55 | F14: Primary | G14: 17 | H14: 2.8 | I14: Maund | J14: 104.5 | K14: 7 | L14: 265 | M14: 220 | N14: 30 | O14: 8 | P14: Fisherman | Q14: Hawker | R14: 55 | S14: 25 | T14: 20 | U14: Regular | V14: No | W14: Competition from frozen imported fish | X14: Day-to-day price volatility | Y14: Low landings in lean season
B15: M2-R-05 | C15: M2 | D15: 46085 | E15: 27 | F15: Secondary | G15: 6 | H15: 2.7 | I15: Maund | J15: 100.76 | K15: 6 | L15: 300 | M15: 175 | N15: 85 | O15: 6 | P15: Fisherman | Q15: Household | R15: 69 | S15: 15 | T15: 16 | U15: Regular | V15: No | W15: Rising cost of ice and salt | X15: Unsold fish spoilage loss | Y15: Delayed credit recovery | Z15: PAIR-M2-02
B16: M2-R-06 | C16: M2
B17: M3-R-01 | C17: M3 | D17: 46086 | E17: 51 | F17: Secondary | G17: 25 | H17: 150 | I17: Kg | J17: 150 | K17: 8 | L17: 115 | M17: 195 | N17: 60 | O17: 6 | P17: Fisherman | Q17: Hotel | R17: 52 | S17: 36 | T17: 12 | U17: Regular | V17: No | W17: Waterlogging during monsoon | X17: Competition from frozen imported fish | Y17: Unsold fish spoilage loss
B18: M3-R-02 | C18: M3 | D18: 46086 | E18: 26 | F18: Primary | G18: 4 | H18: 2 | I18: Maund | J18: 74.64 | K18: 8 | L18: 155 | M18: 240 | N18: 30 | O18: 4 | P18: Aratdar | Q18: Household | R18: 56 | S18: 29 | T18: 15 | U18: Occasional | V18: Some | W18: Waterlogging during monsoon | X18: Rising toll and lease burden | Y18: Unsold fish spoilage loss
B19: M3-R-03 | C19: M3 | D19: 46086 | E19: 53 | F19: Secondary | G19: 9 | H19: 143 | I19: Kg | J19: 143 | K19: 3 | L19: 235 | M19: 210 | N19: 100 | O19: 6 | P19: Aratdar | Q19: Hotel | R19: 56 | S19: 38 | T19: 6 | U19: Regular | V19: Some | W19: Waterlogging during monsoon | X19: Delayed credit recovery | Y19: High ice price | Z19: PAIR-M3-01
B20: M3-R-04 | C20: M3 | D20: 46086 | E20: 40 | F20: Secondary | G20: 2 | H20: 135 | I20: Kg | J20: 135 | K20: 4 | L20: 200 | M20: 185 | N20: 105 | O20: 5 | P20: Aratdar | Q20: Institutional | R20: 54 | S20: 30 | T20: 16 | U20: Regular | V20: Some | W20: Day-to-day price volatility | X20: Rising cost of ice and salt | Y20: Low landings in lean season | Z20: PAIR-M3-02
B21: M3-R-05 | C21: M3 | D21: 46086 | E21: 21 | F21: Higher_Secondary | G21: 5 | H21: 137 | I21: Kg | J21: 137 | K21: 6 | L21: 290 | M21: 90 | N21: 30 | O21: 7 | P21: Aratdar | Q21: Household | R21: 41 | S21: 31 | T21: 28 | U21: Occasional | V21: Some | W21: High ice price | X21: Waterlogging during monsoon | Y21: Day-to-day price volatility
B22: M3-R-06 | C22: M3
B23: M4-R-01 | C23: M4 | D23: 46087 | E23: 27 | F23: Primary | G23: 11 | H23: 1.8 | I23: Maund | J23: 67.18 | K23: 7 | L23: 285 | M23: 240 | N23: 80 | O23: 5 | P23: Aratdar | Q23: Household | R23: 62 | S23: 27 | T23: 11 | U23: Regular | V23: Some | W23: Competition from frozen imported fish | X23: Day-to-day price volatility | Y23: Irregular electricity and load-shedding | Z23: PAIR-M4-01
B24: M4-R-02 | C24: M4 | D24: 46087 | E24: 34 | F24: Secondary | G24: 18 | H24: 60 | I24: Kg | J24: 60 | K24: 8 | L24: 140 | M24: 130 | N24: 90 | O24: 6 | P24: Aratdar | Q24: Institutional | R24: 57 | S24: 17 | T24: 26 | U24: Regular | V24: Some | W24: Delayed credit recovery | X24: Day-to-day price volatility | Y24: Supply syndicate control | Z24: PAIR-M4-03
B25: M4-R-03 | C25: M4 | D25: 46087 | E25: 53 | F25: Primary | G25: 27 | H25: 139 | I25: Kg | J25: 139 | K25: 6 | L25: 145 | M25: 140 | N25: 115 | O25: 8 | P25: Aratdar | Q25: Household | R25: 44 | S25: 40 | T25: 16 | U25: Regular | V25: Almost_all | W25: Day-to-day price volatility | X25: Low landings in lean season | Y25: Transport cost increase
B26: M4-R-04 | C26: M4 | D26: 46087 | E26: 25 | F26: Secondary | G26: 5 | H26: 47 | I26: Kg | J26: 47 | K26: 8 | L26: 225 | M26: 215 | N26: 115 | O26: 4 | P26: Aratdar | Q26: Household | R26: 44 | S26: 15 | T26: 41 | U26: Regular | V26: Some | W26: Competition from frozen imported fish | X26: Rising cost of ice and salt | Y26: Supply syndicate control
B27: M4-R-05 | C27: M4 | D27: 46087 | E27: 40 | F27: Primary | G27: 13 | H27: 136 | I27: Kg | J27: 136 | K27: 8 | L27: 265 | M27: 120 | N27: 45 | O27: 3 | P27: Aratdar | Q27: Household | R27: 68 | S27: 19 | T27: 13 | U27: Never | V27: Some | W27: Unsold fish spoilage loss | X27: Transport cost increase | Y27: Delayed credit recovery | Z27: PAIR-M4-02
B28: M4-R-06 | C28: M4
B29: M5-R-01 | C29: M5 | D29: 46088 | E29: 34 | F29: Illiterate | G29: 9 | H29: 106 | I29: Kg | J29: 106 | K29: 4 | L29: 120 | M29: 100 | N29: 145 | O29: 6 | P29: Aratdar | Q29: Other | R29: 54 | S29: 21 | T29: 25 | U29: Regular | V29: Some | W29: Transport cost increase | X29: High ice price | Y29: Rising cost of ice and salt | Z29: PAIR-M5-03
B30: M5-R-02 | C30: M5 | D30: 46088 | E30: 27 | F30: Secondary | G30: 11 | H30: 56 | I30: Kg | J30: 56 | K30: 3 | L30: 300 | M30: 100 | N30: 40 | O30: 7 | P30: Other | Q30: Household | R30: 44 | S30: 43 | T30: 13 | U30: Regular | V30: Some | W30: Rising cost of ice and salt | X30: Irregular electricity and load-shedding | Y30: Low landings in lean season | Z30: PAIR-M5-02
B31: M5-R-03 | C31: M5 | D31: 46088 | E31: 50 | F31: Secondary | G31: 20 | H31: 64 | I31: Kg | J31: 64 | K31: 3 | L31: 315 | M31: 160 | N31: 45 | O31: 4 | P31: Aratdar | Q31: Hotel | R31: 48 | S31: 32 | T31: 20 | U31: Occasional | V31: Some | W31: Unsold fish spoilage loss | X31: Low landings in lean season | Y31: High ice price
B32: M5-R-04 | C32: M5 | D32: 46088 | E32: 43 | F32: Illiterate | G32: 14 | H32: 64 | I32: Kg | J32: 64 | K32: 4 | L32: 350 | M32: 105 | N32: 115 | O32: 8 | P32: Aratdar | Q32: Hawker | R32: 63 | S32: 16 | T32: 21 | U32: Never | V32: Almost_all | W32: Rising cost of ice and salt | X32: Irregular electricity and load-shedding | Y32: Transport cost increase | Z32: PAIR-M5-01
B33: M5-R-05 | C33: M5 | D33: 46088 | E33: 35 | F33: Primary | G33: 8 | H33: 115 | I33: Kg | J33: 115 | K33: 6 | L33: 110 | M33: 165 | N33: 135 | O33: 8 | P33: Aratdar | Q33: Household | R33: 63 | S33: 30 | T33: 7 | U33: Occasional | V33: Some | W33: Rising toll and lease burden | X33: Day-to-day price volatility | Y33: Unsold fish spoilage loss
B34: M5-R-06 | C34: M5
B35: M6-R-01 | C35: M6 | D35: 46084 | E35: 47 | F35: Higher_Secondary | G35: 28 | H35: 56 | I35: Kg | J35: 56 | K35: 8 | L35: 80 | M35: 100 | N35: 125 | O35: 3 | P35: Aratdar | Q35: Household | R35: 48 | S35: 22 | T35: 30 | U35: Occasional | V35: Some | W35: Transport cost increase | X35: Day-to-day price volatility | Y35: Rising cost of ice and salt | Z35: PAIR-M6-01
B36: M6-R-02 | C36: M6 | D36: 46084 | E36: 32 | F36: Primary | G36: 12 | H36: 2.8 | I36: Maund | J36: 104.5 | K36: 6 | L36: 85 | M36: 185 | N36: 80 | O36: 7 | P36: Fisherman | Q36: Household | R36: 67 | S36: 28 | T36: 5 | U36: Regular | V36: No | W36: Transport cost increase | X36: High ice price | Y36: Unsold fish spoilage loss
B37: M6-R-03 | C37: M6 | D37: 46084 | E37: 38 | F37: Secondary | G37: 12 | H37: 116 | I37: Kg | J37: 116 | K37: 4 | L37: 70 | M37: 135 | N37: 60 | O37: 5 | P37: Aratdar | Q37: Other | R37: 62 | S37: 15 | T37: 23 | U37: Regular | V37: Some | W37: Irregular electricity and load-shedding | X37: Transport cost increase | Y37: Delayed credit recovery
B38: M6-R-04 | C38: M6 | D38: 46084 | E38: 47 | F38: Illiterate | G38: 16 | H38: 44 | I38: Kg | J38: 44 | K38: 2 | L38: 180 | M38: 250 | N38: 30 | O38: 3 | P38: Faria | Q38: Household | R38: 64 | S38: 30 | T38: 6 | U38: Never | V38: Some | W38: High ice price | X38: Supply syndicate control | Y38: Rising toll and lease burden | Z38: PAIR-M6-02
B39: M6-R-05 | C39: M6 | D39: 46084 | E39: 50 | F39: Secondary | G39: 7 | H39: 135 | I39: Kg | J39: 135 | K39: 7 | L39: 295 | M39: 245 | N39: 70 | O39: 8 | P39: Fisherman | Q39: Hotel | R39: 59 | S39: 36 | T39: 5 | U39: Occasional | V39: Almost_all | W39: Transport cost increase | X39: Day-to-day price volatility | Y39: Rising cost of ice and salt
B40: M6-R-06 | C40: M6

Sheet Form_C_Consumer
B2: Form C - Fish Buyer Exit Slip (one respondent per row)
B4: Respondent_ID | C4: Market | D4: Interview_Date | E4: Interview_time | F4: Consent_given | G4: Visit_frequency | H4: Visit_interval_days | I4: Payment_method | J4: Main_reason_choosing_arat | K4: Pair_ID | L4: Notes
B5: M1-C-01 | C5: M1 | D5: 46084 | E5: 09:45 | F5: Yes | G5: Daily | H5: 1 | I5: Cash | J5: Purity
B6: M1-C-02 | C6: M1 | D6: 46084 | E6: 12:05 | F6: Yes | G6: Weekly | H6: 7 | I6: Nagad_app | J6: Purity
B7: M1-C-03 | C7: M1 | D7: 46084 | E7: 09:55 | F7: Yes | G7: Weekly | H7: 5 | I7: Credit | J7: Purity
B8: M1-C-04 | C8: M1 | D8: 46084 | E8: 09:30 | F8: Yes | G8: Weekly | H8: 5 | I8: Cash | J8: Price
B9: M1-C-05 | C9: M1 | D9: 46084 | E9: 12:05 | F9: Yes | G9: Weekly | H9: 7 | I9: bKash | J9: Price
B10: M1-C-06 | C10: M1
B11: M2-C-01 | C11: M2 | D11: 46085 | E11: 12:25 | F11: Yes | G11: Daily | H11: 2 | I11: Cash | J11: Purity
B12: M2-C-02 | C12: M2 | D12: 46085 | E12: 11:50 | F12: Yes | G12: Weekly | H12: 7 | I12: Cash | J12: Proximity
B13: M2-C-03 | C13: M2 | D13: 46085 | E13: 09:15 | F13: Yes | G13: Daily | H13: 2 | I13: bKash | J13: Familiar_shop
B14: M2-C-04 | C14: M2 | D14: 46085 | E14: 09:25 | F14: Yes | G14: Weekly | H14: 7 | I14: Nagad_app | J14: Purity
B15: M2-C-05 | C15: M2 | D15: 46085 | E15: 08:45 | F15: Yes | G15: Daily | H15: 2 | I15: Cash | J15: Price
B16: M2-C-06 | C16: M2
B17: M3-C-01 | C17: M3 | D17: 46086 | E17: 09:15 | F17: Yes | G17: Daily | H17: 2 | I17: Cash | J17: Purity
B18: M3-C-02 | C18: M3 | D18: 46086 | E18: 09:15 | F18: Yes | G18: Weekly | H18: 4 | I18: Cash | J18: Familiar_shop
B19: M3-C-03 | C19: M3 | D19: 46086 | E19: 12:25 | F19: Yes | G19: Weekly | H19: 5 | I19: Cash | J19: Familiar_shop
B20: M3-C-04 | C20: M3 | D20: 46086 | E20: 09:45 | F20: Yes | G20: Weekly | H20: 6 | I20: Credit | J20: Familiar_shop
B21: M3-C-05 | C21: M3 | D21: 46086 | E21: 09:30 | F21: Yes | G21: Daily | H21: 1 | I21: Cash | J21: Proximity
B22: M3-C-06 | C22: M3
B23: M4-C-01 | C23: M4 | D23: 46087 | E23: 10:40 | F23: Yes | G23: Weekly | H23: 6 | I23: Nagad_app | J23: Proximity
B24: M4-C-02 | C24: M4 | D24: 46087 | E24: 08:35 | F24: Yes | G24: Weekly | H24: 5 | I24: Cash | J24: Variety
B25: M4-C-03 | C25: M4 | D25: 46087 | E25: 08:50 | F25: Yes | G25: Weekly | H25: 7 | I25: bKash | J25: Familiar_shop
B26: M4-C-04 | C26: M4 | D26: 46087 | E26: 08:40 | F26: Yes | G26: Daily | H26: 2 | I26: Cash | J26: Other
B27: M4-C-05 | C27: M4 | D27: 46087 | E27: 09:50 | F27: Yes | G27: Weekly | H27: 7 | I27: bKash | J27: Purity
B28: M4-C-06 | C28: M4
B29: M5-C-01 | C29: M5 | D29: 46088 | E29: 11:45 | F29: Yes | G29: Daily | H29: 2 | I29: Nagad_app | J29: Purity
B30: M5-C-02 | C30: M5 | D30: 46088 | E30: 12:20 | F30: Yes | G30: Weekly | H30: 5 | I30: Cash | J30: Purity
B31: M5-C-03 | C31: M5 | D31: 46088 | E31: 09:15 | F31: Yes | G31: Weekly | H31: 4 | I31: Nagad_app | J31: Purity
B32: M5-C-04 | C32: M5 | D32: 46088 | E32: 08:30 | F32: Yes | G32: Weekly | H32: 5 | I32: Cash | J32: Proximity
B33: M5-C-05 | C33: M5 | D33: 46088 | E33: 10:15 | F33: Yes | G33: Weekly | H33: 7 | I33: Nagad_app | J33: Price
B34: M5-C-06 | C34: M5
B35: M6-C-01 | C35: M6 | D35: 46084 | E35: 10:25 | F35: Yes | G35: Weekly | H35: 6 | I35: bKash | J35: Price
B36: M6-C-02 | C36: M6 | D36: 46084 | E36: 08:10 | F36: Yes | G36: Weekly | H36: 4 | I36: bKash | J36: Proximity
B37: M6-C-03 | C37: M6 | D37: 46084 | E37: 12:15 | F37: Yes | G37: Weekly | H37: 6 | I37: Cash | J37: Other
B38: M6-C-04 | C38: M6 | D38: 46084 | E38: 08:00 | F38: Yes | G38: Weekly | H38: 7 | I38: Nagad_app | J38: Purity
B39: M6-C-05 | C39: M6 | D39: 46084 | E39: 09:55 | F39: Yes | G39: Weekly | H39: 4 | I39: Cash | J39: Familiar_shop
B40: M6-C-06 | C40: M6

Sheet Price_Observations
B2: Price Observations - one row per respondent x species quote (core dataset)
B4: Obs_ID | C4: Respondent_ID | D4: Market | E4: Actor_type | F4: Species_code | G4: Buy_price_raw | H4: Sell_price_raw | I4: Unit | J4: Buy_BDT_per_kg | K4: Sell_BDT_per_kg | L4: Quantity_raw | M4: Quantity_unit | N4: Quantity_kg | O4: Pair_ID | P4: Notes
B5: PO-0001 | C5: M1-A-01 | D5: M1 | E5: Aratdar | F5: S01 | G5: 36750 | H5: 38500 | I5: Maund | J5: 984.73 | K5: 1031.62 | L5: 3.6 | M5: Maund | N5: 134.35
B6: PO-0002 | C6: M1-A-01 | D6: M1 | E6: Aratdar | F6: S02 | G6: 43000 | H6: 45000 | I6: Maund | J6: 1152.2 | K6: 1205.79 | L6: 4 | M6: Maund | N6: 149.28
B7: PO-0003 | C7: M1-A-01 | D7: M1 | E7: Aratdar | F7: S05 | G7: 14750 | H7: 15500 | I7: Maund | J7: 395.23 | K7: 415.33 | L7: 2.6 | M7: Maund | N7: 97.03
B8: PO-0004 | C8: M1-A-01 | D8: M1 | E8: Aratdar | F8: S06 | G8: 12250 | H8: 13000 | I8: Maund | J8: 328.24 | K8: 348.34 | L8: 3.7 | M8: Maund | N8: 138.08 | O8: PAIR-M1-02
B9: PO-0005 | C9: M1-A-01 | D9: M1 | E9: Aratdar | F9: S09 | G9: 7400 | H9: 7700 | I9: Maund | J9: 198.29 | K9: 206.32 | L9: 3 | M9: Maund | N9: 111.96
B10: PO-0006 | C10: M1-A-01 | D10: M1 | E10: Aratdar | F10: S07 | G10: K | H10: K | P10: Species not handled today
B11: PO-0007 | C11: M1-A-01 | D11: M1 | E11: Aratdar | F11: S03 | G11: K | H11: K | P11: Species not handled today
B12: PO-0008 | C12: M1-A-02 | D12: M1 | E12: Aratdar | F12: S01 | G12: 37750 | H12: 39500 | I12: Maund | J12: 1011.52 | K12: 1058.41 | L12: 3.6 | M12: Maund | N12: 134.35
B13: PO-0009 | C13: M1-A-02 | D13: M1 | E13: Aratdar | F13: S03 | G13: 28250 | H13: 29750 | I13: Maund | J13: 756.97 | K13: 797.16 | L13: 4.6 | M13: Maund | N13: 171.67
B14: PO-0010 | C14: M1-A-02 | D14: M1 | E14: Aratdar | F14: S04 | G14: 24000 | H14: 24750 | I14: Maund | J14: 643.09 | K14: 663.18 | L14: 3.3 | M14: Maund | N14: 123.16
B15: PO-0011 | C15: M1-A-02 | D15: M1 | E15: Aratdar | F15: S05 | G15: 15000 | H15: 15500 | I15: Maund | J15: 401.93 | K15: 415.33 | L15: 2.9 | M15: Maund | N15: 108.23
B16: PO-0012 | C16: M1-A-02 | D16: M1 | E16: Aratdar | F16: S06 | G16: 11750 | H16: 12000 | I16: Maund | J16: 314.84 | K16: 321.54 | L16: 3.2 | M16: Maund | N16: 119.42
B17: PO-0013 | C17: M1-A-02 | D17: M1 | E17: Aratdar | F17: S02 | G17: K | H17: K | P17: Species not handled today
B18: PO-0014 | C18: M1-A-02 | D18: M1 | E18: Aratdar | F18: S09 | G18: K | H18: K | P18: Species not handled today
B19: PO-0015 | C19: M1-A-03 | D19: M1 | E19: Aratdar | F19: S01 | G19: 37000 | H19: 38000 | I19: Maund | J19: 991.43 | K19: 1018.22 | L19: 2.4 | M19: Maund | N19: 89.57
B20: PO-0016 | C20: M1-A-03 | D20: M1 | E20: Aratdar | F20: S02 | G20: 40750 | H20: 42000 | I20: Maund | J20: 1091.91 | K20: 1125.4 | L20: 1.8 | M20: Maund | N20: 67.18
B21: PO-0017 | C21: M1-A-03 | D21: M1 | E21: Aratdar | F21: S04 | G21: 24750 | H21: 26000 | I21: Maund | J21: 663.18 | K21: 696.68 | L21: 3.8 | M21: Maund | N21: 141.82
B22: PO-0018 | C22: M1-A-03 | D22: M1 | E22: Aratdar | F22: S05 | G22: 15500 | H22: 16250 | I22: Maund | J22: 415.33 | K22: 435.42 | L22: 2.5 | M22: Maund | N22: 93.3
B23: PO-0019 | C23: M1-A-03 | D23: M1 | E23: Aratdar | F23: S08 | G23: 9600 | H23: 10000 | I23: Maund | J23: 257.23 | K23: 267.95 | L23: 1.9 | M23: Maund | N23: 70.91
B24: PO-0020 | C24: M1-A-04 | D24: M1 | E24: Aratdar | F24: S01 | G24: 37000 | H24: 39250 | I24: Maund | J24: 991.43 | K24: 1051.71 | L24: 2.2 | M24: Maund | N24: 82.1
B25: PO-0021 | C25: M1-A-04 | D25: M1 | E25: Aratdar | F25: S02 | G25: 44250 | H25: 46750 | I25: Maund | J25: 1185.69 | K25: 1252.68 | L25: 2.3 | M25: Maund | N25: 85.84
B26: PO-0022 | C26: M1-A-04 | D26: M1 | E26: Aratdar | F26: S03 | G26: 29250 | H26: 30750 | I26: Maund | J26: 783.76 | K26: 823.95 | L26: 2.4 | M26: Maund | N26: 89.57
B27: PO-0023 | C27: M1-A-04 | D27: M1 | E27: Aratdar | F27: S06 | G27: 12000 | H27: 12750 | I27: Maund | J27: 321.54 | K27: 341.64 | L27: 1.8 | M27: Maund | N27: 67.18
B28: PO-0024 | C28: M1-A-04 | D28: M1 | E28: Aratdar | F28: S07 | G28: 13750 | H28: 14500 | I28: Maund | J28: 368.44 | K28: 388.53 | L28: 1.4 | M28: Maund | N28: 52.25
B29: PO-0025 | C29: M1-A-05 | D29: M1 | E29: Aratdar | F29: S01 | G29: 40250 | H29: 41750 | I29: Maund | J29: 1078.51 | K29: 1118.7 | L29: 6.4 | M29: Maund | N29: 238.85
B30: PO-0026 | C30: M1-A-05 | D30: M1 | E30: Aratdar | F30: S02 | G30: 40500 | H30: 42500 | I30: Maund | J30: 1085.21 | K30: 1138.8 | L30: 4.9 | M30: Maund | N30: 182.87
B31: PO-0027 | C31: M1-A-05 | D31: M1 | E31: Aratdar | F31: S03 | G31: 28000 | H31: 29250 | I31: Maund | J31: 750.27 | K31: 783.76 | L31: 6 | M31: Maund | N31: 223.92 | O31: PAIR-M1-01
B32: PO-0028 | C32: M1-A-05 | D32: M1 | E32: Aratdar | F32: S05 | G32: 15250 | H32: 16000 | I32: Maund | J32: 408.63 | K32: 428.72 | L32: 4.5 | M32: Maund | N32: 167.94
B33: PO-0029 | C33: M1-A-05 | D33: M1 | E33: Aratdar | F33: S06 | G33: 11750 | H33: 12250 | I33: Maund | J33: 314.84 | K33: 328.24 | L33: 5.4 | M33: Maund | N33: 201.53
B34: PO-0030 | C34: M1-B-01 | D34: M1 | E34: Bepari_Faria | F34: S05 | G34: 16250 | H34: 17250 | I34: Maund | J34: 435.42 | K34: 462.22 | L34: 1.1 | M34: Maund | N34: 41.05
B35: PO-0031 | C35: M1-B-01 | D35: M1 | E35: Bepari_Faria | F35: S07 | G35: 13750 | H35: 15500 | I35: Maund | J35: 368.44 | K35: 415.33 | L35: 1.3 | M35: Maund | N35: 48.52
B36: PO-0032 | C36: M1-B-01 | D36: M1 | E36: Bepari_Faria | F36: S08 | G36: 9300 | H36: 10250 | I36: Maund | J36: 249.2 | K36: 274.65 | L36: 1.2 | M36: Maund | N36: 44.78
B37: PO-0033 | C37: M1-B-01 | D37: M1 | E37: Bepari_Faria | F37: S09 | G37: 7700 | H37: 8500 | I37: Maund | J37: 206.32 | K37: 227.76 | L37: 0.9 | M37: Maund | N37: 33.59
B38: PO-0034 | C38: M1-B-01 | D38: M1 | E38: Bepari_Faria | F38: S03 | G38: K | H38: K | P38: Species not handled today
B39: PO-0035 | C39: M1-B-01 | D39: M1 | E39: Bepari_Faria | F39: S02 | G39: K | H39: K | P39: Species not handled today
B40: PO-0036 | C40: M1-B-02 | D40: M1 | E40: Bepari_Faria | F40: S04 | G40: 24000 | H40: 26000 | I40: Maund | J40: 643.09 | K40: 696.68 | L40: 1.9 | M40: Maund | N40: 70.91
B41: PO-0037 | C41: M1-B-02 | D41: M1 | E41: Bepari_Faria | F41: S05 | G41: 15250 | H41: 17250 | I41: Maund | J41: 408.63 | K41: 462.22 | L41: 1.7 | M41: Maund | N41: 63.44
B42: PO-0038 | C42: M1-B-02 | D42: M1 | E42: Bepari_Faria | F42: S06 | G42: 12500 | H42: 13500 | I42: Maund | J42: 334.94 | K42: 361.74 | L42: 0.8 | M42: Maund | N42: 29.86
B43: PO-0039 | C43: M1-B-02 | D43: M1 | E43: Bepari_Faria | F43: S08 | G43: 9000 | H43: 9800 | I43: Maund | J43: 241.16 | K43: 262.59 | L43: 1 | M43: Maund | N43: 37.32
B44: PO-0040 | C44: M1-B-02 | D44: M1 | E44: Bepari_Faria | F44: S09 | G44: 7200 | H44: 7800 | I44: Maund | J44: 192.93 | K44: 209 | L44: 1.1 | M44: Maund | N44: 41.05
B45: PO-0041 | C45: M1-B-03 | D45: M1 | E45: Bepari_Faria | F45: S01 | G45: 37500 | H45: 42000 | I45: Maund | J45: 1004.82 | K45: 1125.4 | L45: 1 | M45: Maund | N45: 37.32
B46: PO-0042 | C46: M1-B-03 | D46: M1 | E46: Bepari_Faria | F46: S05 | G46: 16500 | H46: 17500 | I46: Maund | J46: 442.12 | K46: 468.92 | L46: 1.1 | M46: Maund | N46: 41.05
B47: PO-0043 | C47: M1-B-03 | D47: M1 | E47: Bepari_Faria | F47: S06 | G47: 13000 | H47: 14000 | I47: Maund | J47: 348.34 | K47: 375.13 | L47: 0.9 | M47: Maund | N47: 33.59
B48: PO-0044 | C48: M1-B-03 | D48: M1 | E48: Bepari_Faria | F48: S07 | G48: 13750 | H48: 15000 | I48: Maund | J48: 368.44 | K48: 401.93 | L48: 0.8 | M48: Maund | N48: 29.86
B49: PO-0045 | C49: M1-B-03 | D49: M1 | E49: Bepari_Faria | F49: S09 | G49: 7600 | H49: 8200 | I49: Maund | J49: 203.64 | K49: 219.72 | L49: 0.7 | M49: Maund | N49: 26.12
B50: PO-0046 | C50: M1-B-03 | D50: M1 | E50: Bepari_Faria | F50: S08 | G50: K | H50: K | P50: Species not handled today
B51: PO-0047 | C51: M1-B-03 | D51: M1 | E51: Bepari_Faria | F51: S02 | G51: K | H51: K | P51: Species not handled today
B52: PO-0048 | C52: M1-B-04 | D52: M1 | E52: Bepari_Faria | F52: S01 | G52: 38750 | H52: 42250 | I52: Maund | J52: 1038.32 | K52: 1132.1 | L52: 0.9 | M52: Maund | N52: 33.59
B53: PO-0049 | C53: M1-B-04 | D53: M1 | E53: Bepari_Faria | F53: S02 | G53: 46500 | H53: 52000 | I53: Maund | J53: 1245.98 | K53: 1393.35 | L53: 0.8 | M53: Maund | N53: 29.86
B54: PO-0050 | C54: M1-B-04 | D54: M1 | E54: Bepari_Faria | F54: S05 | G54: 16250 | H54: 18250 | I54: Maund | J54: 435.42 | K54: 489.01 | L54: 0.4 | M54: Maund | N54: 14.93
B55: PO-0051 | C55: M1-B-04 | D55: M1 | E55: Bepari_Faria | F55: S06 | G55: 12500 | H55: 14000 | I55: Maund | J55: 334.94 | K55: 375.13 | L55: 0.8 | M55: Maund | N55: 29.86
B56: PO-0052 | C56: M1-B-04 | D56: M1 | E56: Bepari_Faria | F56: S07 | G56: 14500 | H56: 16000 | I56: Maund | J56: 388.53 | K56: 428.72 | L56: 0.9 | M56: Maund | N56: 33.59
B57: PO-0053 | C57: M1-B-05 | D57: M1 | E57: Bepari_Faria | F57: S02 | G57: 42250 | H57: 45750 | I57: Maund | J57: 1132.1 | K57: 1225.88 | L57: 0.7 | M57: Maund | N57: 26.12
B58: PO-0054 | C58: M1-B-05 | D58: M1 | E58: Bepari_Faria | F58: S03 | G58: 30500 | H58: 33250 | I58: Maund | J58: 817.26 | K58: 890.94 | L58: 0.7 | M58: Maund | N58: 26.12
B59: PO-0055 | C59: M1-B-05 | D59: M1 | E59: Bepari_Faria | F59: S04 | G59: 25250 | H59: 27250 | I59: Maund | J59: 676.58 | K59: 730.17 | L59: 0.8 | M59: Maund | N59: 29.86
B60: PO-0056 | C60: M1-B-05 | D60: M1 | E60: Bepari_Faria | F60: S05 | G60: 16250 | H60: 18000 | I60: Maund | J60: 435.42 | K60: 482.32 | L60: 0.8 | M60: Maund | N60: 29.86
B61: PO-0057 | C61: M1-B-05 | D61: M1 | E61: Bepari_Faria | F61: S07 | G61: 14000 | H61: 15750 | I61: Maund | J61: 375.13 | K61: 422.03 | L61: 0.6 | M61: Maund | N61: 22.39
B62: PO-0058 | C62: M1-B-05 | D62: M1 | E62: Bepari_Faria | F62: S06 | G62: K | H62: K | P62: Species not handled today
B63: PO-0059 | C63: M1-B-05 | D63: M1 | E63: Bepari_Faria | F63: S10 | G63: K | H63: K | P63: Species not handled today
B64: PO-0060 | C64: M1-R-01 | D64: M1 | E64: Khuchra | F64: S01 | G64: 1185 | H64: 1365 | I64: Kg | J64: 1185 | K64: 1365 | L64: 15 | M64: Kg | N64: 15
B65: PO-0061 | C65: M1-R-01 | D65: M1 | E65: Khuchra | F65: S04 | G65: 740 | H65: 835 | I65: Kg | J65: 740 | K65: 835 | L65: 10 | M65: Kg | N65: 10
B66: PO-0062 | C66: M1-R-01 | D66: M1 | E66: Khuchra | F66: S05 | G66: 470 | H66: 525 | I66: Kg | J66: 470 | K66: 525 | L66: 10 | M66: Kg | N66: 10
B67: PO-0063 | C67: M1-R-01 | D67: M1 | E67: Khuchra | F67: S07 | G67: 435 | H67: 505 | I67: Kg | J67: 435 | K67: 505 | L67: 5 | M67: Kg | N67: 5
B68: PO-0064 | C68: M1-R-01 | D68: M1 | E68: Khuchra | F68: S09 | G68: 225 | H68: 245 | I68: Kg | J68: 225 | K68: 245 | L68: 10 | M68: Kg | N68: 10
B69: PO-0065 | C69: M1-R-02 | D69: M1 | E69: Khuchra | F69: S01 | G69: 1145 | H69: 1320 | I69: Kg | J69: 1145 | K69: 1320 | L69: 20 | M69: Kg | N69: 20
B70: PO-0066 | C70: M1-R-02 | D70: M1 | E70: Khuchra | F70: S04 | G70: 720 | H70: 815 | I70: Kg | J70: 720 | K70: 815 | L70: 20 | M70: Kg | N70: 20
B71: PO-0067 | C71: M1-R-02 | D71: M1 | E71: Khuchra | F71: S06 | G71: 350 | H71: 430 | I71: Kg | J71: 350 | K71: 430 | L71: 20 | M71: Kg | N71: 20 | O71: PAIR-M1-02
B72: PO-0068 | C72: M1-R-02 | D72: M1 | E72: Khuchra | F72: S07 | G72: 415 | H72: 475 | I72: Kg | J72: 415 | K72: 475 | L72: 35 | M72: Kg | N72: 35
B73: PO-0069 | C73: M1-R-02 | D73: M1 | E73: Khuchra | F73: S09 | G73: 220 | H73: 240 | I73: Kg | J73: 220 | K73: 240 | L73: 40 | M73: Kg | N73: 40
B74: PO-0070 | C74: M1-R-03 | D74: M1 | E74: Khuchra | F74: S01 | G74: 1130 | H74: 1270 | I74: Kg | J74: 1130 | K74: 1270 | L74: 10 | M74: Kg | N74: 10
B75: PO-0071 | C75: M1-R-03 | D75: M1 | E75: Khuchra | F75: S02 | G75: 1355 | H75: 1575 | I75: Kg | J75: 1355 | K75: 1575 | L75: 5 | M75: Kg | N75: 5
B76: PO-0072 | C76: M1-R-03 | D76: M1 | E76: Khuchra | F76: S04 | G76: 735 | H76: K | I76: Kg | J76: 735 | L76: 5 | M76: Kg | N76: 5
B77: PO-0073 | C77: M1-R-03 | D77: M1 | E77: Khuchra | F77: S05 | G77: 485 | H77: 535 | I77: Kg | J77: 485 | K77: 535 | L77: 10 | M77: Kg | N77: 10
B78: PO-0074 | C78: M1-R-03 | D78: M1 | E78: Khuchra | F78: S06 | G78: 365 | H78: 420 | I78: Kg | J78: 365 | K78: 420 | L78: 5 | M78: Kg | N78: 5
B79: PO-0075 | C79: M1-R-04 | D79: M1 | E79: Khuchra | F79: S01 | G79: 1210 | H79: 1390 | I79: Kg | J79: 1210 | K79: 1390 | L79: 15 | M79: Kg | N79: 15
B80: PO-0076 | C80: M1-R-04 | D80: M1 | E80: Khuchra | F80: S02 | G80: 1310 | H80: 1530 | I80: Kg | J80: 1310 | K80: 1530 | L80: 25 | M80: Kg | N80: 25
B81: PO-0077 | C81: M1-R-04 | D81: M1 | E81: Khuchra | F81: S05 | G81: 475 | H81: 535 | I81: Kg | J81: 475 | K81: 535 | L81: 15 | M81: Kg | N81: 15
B82: PO-0078 | C82: M1-R-04 | D82: M1 | E82: Khuchra | F82: S06 | G82: 360 | H82: 425 | I82: Kg | J82: 360 | K82: 425 | L82: 25 | M82: Kg | N82: 25
B83: PO-0079 | C83: M1-R-04 | D83: M1 | E83: Khuchra | F83: S07 | G83: 410 | H83: 470 | I83: Kg | J83: 410 | K83: 470 | L83: 30 | M83: Kg | N83: 30
B84: PO-0080 | C84: M1-R-05 | D84: M1 | E84: Khuchra | F84: S01 | G84: 43500 | H84: 50000 | I84: Maund | J84: 1165.59 | K84: 1339.76 | L84: 0.4 | M84: Maund | N84: 14.93
B85: PO-0081 | C85: M1-R-05 | D85: M1 | E85: Khuchra | F85: S03 | G85: 29250 | H85: 35250 | I85: Maund | J85: 783.76 | K85: 944.53 | L85: 0.4 | M85: Maund | N85: 14.93 | O85: PAIR-M1-01
B86: PO-0082 | C86: M1-R-05 | D86: M1 | E86: Khuchra | F86: S04 | G86: 27500 | H86: 31000 | I86: Maund | J86: 736.87 | K86: 830.65 | L86: 0.5 | M86: Maund | N86: 18.66
B87: PO-0083 | C87: M1-R-05 | D87: M1 | E87: Khuchra | F87: S05 | G87: 17000 | H87: 19250 | I87: Maund | J87: 455.52 | K87: 515.81 | L87: 0.7 | M87: Maund | N87: 26.12
B88: PO-0084 | C88: M1-R-05 | D88: M1 | E88: Khuchra | F88: S07 | G88: 16750 | H88: 18500 | I88: Maund | J88: 448.82 | K88: 495.71 | L88: 0.4 | M88: Maund | N88: 14.93
B89: PO-0085 | C89: M2-A-01 | D89: M2 | E89: Aratdar | F89: S01 | G89: 42750 | H89: 45000 | I89: Maund | J89: 1145.5 | K89: 1205.79 | L89: 4 | M89: Maund | N89: 149.28 | O89: PAIR-M2-02
B90: PO-0086 | C90: M2-A-01 | D90: M2 | E90: Aratdar | F90: S03 | G90: 29000 | H90: 30250 | I90: Maund | J90: 777.06 | K90: 810.56 | L90: 6.6 | M90: Maund | N90: 246.31
B91: PO-0087 | C91: M2-A-01 | D91: M2 | E91: Aratdar | F91: S05 | G91: 16500 | H91: 17250 | I91: Maund | J91: 442.12 | K91: 462.22 | L91: 5.7 | M91: Maund | N91: 212.72
B92: PO-0088 | C92: M2-A-01 | D92: M2 | E92: Aratdar | F92: S10 | G92: 7000 | H92: 7300 | I92: Maund | J92: 187.57 | K92: 195.61 | L92: 7.7 | M92: Maund | N92: 287.36
B93: PO-0089 | C93: M2-A-02 | D93: M2 | E93: Aratdar | F93: S01 | G93: 43000 | H93: 45000 | I93: Maund | J93: 1152.2 | K93: 1205.79 | L93: 4.6 | M93: Maund | N93: 171.67
B94: PO-0090 | C94: M2-A-02 | D94: M2 | E94: Aratdar | F94: S02 | G94: 45750 | H94: 47500 | I94: Maund | J94: 1225.88 | K94: 1272.78 | L94: 5.6 | M94: Maund | N94: 208.99
B95: PO-0091 | C95: M2-A-02 | D95: M2 | E95: Aratdar | F95: S05 | G95: 17250 | H95: 17750 | I95: Maund | J95: 462.22 | K95: 475.62 | L95: 6.4 | M95: Maund | N95: 238.85
B96: PO-0092 | C96: M2-A-02 | D96: M2 | E96: Aratdar | F96: S06 | G96: 13250 | H96: 13750 | I96: Maund | J96: 355.04 | K96: 368.44 | L96: 5.7 | M96: Maund | N96: 212.72
B97: PO-0093 | C97: M2-A-02 | D97: M2 | E97: Aratdar | F97: S08 | G97: 9200 | H97: D | I97: Maund | J97: 246.52 | L97: 6.2 | M97: Maund | N97: 231.38
B98: PO-0094 | C98: M2-A-02 | D98: M2 | E98: Aratdar | F98: S03 | G98: K | H98: K | P98: Species not handled today
B99: PO-0095 | C99: M2-A-03 | D99: M2 | E99: Aratdar | F99: S01 | G99: 39750 | H99: 41750 | I99: Maund | J99: 1065.11 | K99: 1118.7 | L99: 1.7 | M99: Maund | N99: 63.44
B100: PO-0096 | C100: M2-A-03 | D100: M2 | E100: Aratdar | F100: S02 | G100: 47250 | H100: 50000 | I100: Maund | J100: 1266.08 | K100: 1339.76 | L100: 2.1 | M100: Maund | N100: 78.37
B101: PO-0097 | C101: M2-A-03 | D101: M2 | E101: Aratdar | F101: S04 | G101: 27000 | H101: 28000 | I101: Maund | J101: 723.47 | K101: 750.27 | L101: 1.7 | M101: Maund | N101: 63.44
B102: PO-0098 | C102: M2-A-03 | D102: M2 | E102: Aratdar | F102: S06 | G102: 12250 | H102: 13000 | I102: Maund | J102: 328.24 | K102: 348.34 | L102: 2.1 | M102: Maund | N102: 78.37
...

Sheet Consumer_Purchases_Focal
B2: Form C - Focal Species Purchases (one row per consumer x species)
B4: Respondent_ID | C4: Market | D4: Species_code | E4: Purchased_today | F4: Bought_from | G4: Price_raw | H4: Unit | I4: Price_BDT_per_kg | J4: Quantity_raw | K4: Quantity_unit | L4: Quantity_kg | M4: Notes
B5: M1-C-01 | C5: M1 | D5: S07 | E5: Yes | F5: Retailer | G5: 480 | H5: Kg | I5: 480 | J5: 2.5 | K5: Kg | L5: 2.5
B6: M1-C-01 | C6: M1 | D6: S02 | E6: Yes | F6: Retailer | G6: 1490 | H6: Kg | I6: 1490 | J6: 1 | K6: Kg | L6: 1
B7: M1-C-02 | C7: M1 | D7: S04 | E7: Yes | F7: Retailer | G7: 860 | H7: Kg | I7: 860 | J7: 2 | K7: Kg | L7: 2
B8: M1-C-02 | C8: M1 | D8: S01 | E8: Yes | F8: Retailer | G8: 1360 | H8: Kg | I8: 1360 | J8: 0.75 | K8: Kg | L8: 0.75
B9: M1-C-02 | C9: M1 | D9: S02 | E9: Yes | F9: Retailer | G9: 1545 | H9: Kg | I9: 1545 | J9: 2.5 | K9: Kg | L9: 2.5
B10: M1-C-03 | C10: M1 | D10: S05 | E10: Yes | F10: Retailer | G10: 555 | H10: Kg | I10: 555 | J10: 1.5 | K10: Kg | L10: 1.5
B11: M1-C-03 | C11: M1 | D11: S01 | E11: No | G11: K
B12: M1-C-04 | C12: M1 | D12: S03 | E12: Yes | F12: Retailer | G12: 980 | H12: Kg | I12: 980 | J12: 2.5 | K12: Kg | L12: 2.5
B13: M1-C-04 | C13: M1 | D13: S10 | E13: Yes | F13: Retailer | G13: 225 | H13: Kg | I13: 225 | J13: 2 | K13: Kg | L13: 2
B14: M1-C-05 | C14: M1 | D14: S05 | E14: Yes | F14: Retailer | G14: 545 | H14: Kg | I14: 545 | J14: 0.75 | K14: Kg | L14: 0.75
B15: M1-C-05 | C15: M1 | D15: S04 | E15: Yes | F15: Retailer | G15: 875 | H15: Kg | I15: 875 | J15: 3 | K15: Kg | L15: 3
B16: M1-C-05 | C16: M1 | D16: S07 | E16: Yes | F16: Retailer | G16: 495 | H16: Kg | I16: 495 | J16: 1.5 | K16: Kg | L16: 1.5
B17: M2-C-01 | C17: M2 | D17: S01 | E17: Yes | F17: Retailer | G17: 1495 | H17: Kg | I17: 1495 | J17: 2 | K17: Kg | L17: 2
B18: M2-C-01 | C18: M2 | D18: S07 | E18: Yes | F18: Retailer | G18: 520 | H18: Kg | I18: 520 | J18: 2.5 | K18: Kg | L18: 2.5
B19: M2-C-01 | C19: M2 | D19: S05 | E19: No | G19: K
B20: M2-C-01 | C20: M2 | D20: S10 | E20: No | G20: K
B21: M2-C-02 | C21: M2 | D21: S09 | E21: Yes | F21: Hawker | G21: 275 | H21: Kg | I21: 275 | J21: 1 | K21: Kg | L21: 1
B22: M2-C-02 | C22: M2 | D22: S01 | E22: Yes | F22: Retailer | G22: 1460 | H22: Kg | I22: 1460 | J22: 2.5 | K22: Kg | L22: 2.5
B23: M2-C-03 | C23: M2 | D23: S01 | E23: Yes | F23: Retailer | G23: 1475 | H23: Kg | I23: 1475 | J23: 2.5 | K23: Kg | L23: 2.5
B24: M2-C-03 | C24: M2 | D24: S10 | E24: Yes | F24: Retailer | G24: 235 | H24: Kg | I24: 235 | J24: 1.5 | K24: Kg | L24: 1.5
B25: M2-C-03 | C25: M2 | D25: S05 | E25: Yes | F25: Retailer | G25: 575 | H25: Kg | I25: 575 | J25: 2.5 | K25: Kg | L25: 2.5
B26: M2-C-04 | C26: M2 | D26: S05 | E26: Yes | F26: Retailer | G26: 565 | H26: Kg | I26: 565 | J26: 0.75 | K26: Kg | L26: 0.75
B27: M2-C-04 | C27: M2 | D27: S06 | E27: Yes | F27: Retailer | G27: 440 | H27: Kg | I27: 440 | J27: 1.5 | K27: Kg | L27: 1.5
B28: M2-C-04 | C28: M2 | D28: S04 | E28: Yes | F28: Retailer | G28: 895 | H28: Kg | I28: 895 | J28: 1.5 | K28: Kg | L28: 1.5
B29: M2-C-04 | C29: M2 | D29: S09 | E29: No | G29: K
B30: M2-C-04 | C30: M2 | D30: S02 | E30: No | G30: K
B31: M2-C-05 | C31: M2 | D31: S09 | E31: Yes | F31: Retailer | G31: 275 | H31: Kg | I31: 275 | J31: 3 | K31: Kg | L31: 3
B32: M2-C-05 | C32: M2 | D32: S01 | E32: Yes | F32: Retailer | G32: 1425 | H32: Kg | I32: 1425 | J32: 1 | K32: Kg | L32: 1
B33: M2-C-05 | C33: M2 | D33: S08 | E33: Yes | F33: Retailer | G33: 350 | H33: Kg | I33: 350 | J33: 1 | K33: Kg | L33: 1
B34: M2-C-05 | C34: M2 | D34: S05 | E34: No | G34: K
B35: M3-C-01 | C35: M3 | D35: S06 | E35: Yes | F35: Retailer | G35: 460 | H35: Kg | I35: 460 | J35: 1 | K35: Kg | L35: 1
B36: M3-C-01 | C36: M3 | D36: S02 | E36: Yes | F36: Retailer | G36: 1670 | H36: Kg | I36: 1670 | J36: 2 | K36: Kg | L36: 2
B37: M3-C-02 | C37: M3 | D37: S06 | E37: Yes | F37: Retailer | G37: 445 | H37: Kg | I37: 445 | J37: 2.5 | K37: Kg | L37: 2.5
B38: M3-C-02 | C38: M3 | D38: S09 | E38: No | G38: K
B39: M3-C-03 | C39: M3 | D39: S05 | E39: Yes | F39: Retailer | G39: 600 | H39: Kg | I39: 600 | J39: 2.5 | K39: Kg | L39: 2.5
B40: M3-C-03 | C40: M3 | D40: S06 | E40: Yes | F40: Retailer | G40: 445 | H40: Kg | I40: 445 | J40: 3 | K40: Kg | L40: 3
B41: M3-C-03 | C41: M3 | D41: S01 | E41: Yes | F41: Retailer | G41: 1520 | H41: Kg | I41: 1520 | J41: 3 | K41: Kg | L41: 3
B42: M3-C-04 | C42: M3 | D42: S05 | E42: Yes | F42: Retailer | G42: 600 | H42: Kg | I42: 600 | J42: 1 | K42: Kg | L42: 1
B43: M3-C-05 | C43: M3 | D43: S01 | E43: Yes | F43: Retailer | G43: 1495 | H43: Kg | I43: 1495 | J43: 1.5 | K43: Kg | L43: 1.5
B44: M4-C-01 | C44: M4 | D44: S05 | E44: Yes | F44: Retailer | G44: 585 | H44: Kg | I44: 585 | J44: 2.5 | K44: Kg | L44: 2.5
B45: M4-C-02 | C45: M4 | D45: S01 | E45: Yes | F45: Retailer | G45: 1475 | H45: Kg | I45: 1475 | J45: 0.5 | K45: Kg | L45: 0.5
B46: M4-C-02 | C46: M4 | D46: S10 | E46: Yes | F46: Retailer | G46: 230 | H46: Kg | I46: 230 | J46: 1 | K46: Kg | L46: 1
B47: M4-C-03 | C47: M4 | D47: S07 | E47: Yes | F47: Retailer | G47: 520 | H47: Kg | I47: 520 | J47: 3 | K47: Kg | L47: 3
B48: M4-C-04 | C48: M4 | D48: S06 | E48: Yes | F48: Hawker | G48: 450 | H48: Kg | I48: 450 | J48: 2.5 | K48: Kg | L48: 2.5
B49: M4-C-05 | C49: M4 | D49: S06 | E49: Yes | F49: Retailer | G49: 440 | H49: Kg | I49: 440 | J49: 3 | K49: Kg | L49: 3
B50: M4-C-05 | C50: M4 | D50: S01 | E50: Yes | F50: Retailer | G50: 1485 | H50: Kg | I50: 1485 | J50: 3 | K50: Kg | L50: 3
B51: M4-C-05 | C51: M4 | D51: S05 | E51: No | G51: K
B52: M5-C-01 | C52: M5 | D52: S05 | E52: Yes | F52: Retailer | G52: 615 | H52: Kg | I52: 615 | J52: 1 | K52: Kg | L52: 1
B53: M5-C-02 | C53: M5 | D53: S06 | E53: Yes | F53: Retailer | G53: 465 | H53: Kg | I53: 465 | J53: 0.5 | K53: Kg | L53: 0.5
B54: M5-C-02 | C54: M5 | D54: S09 | E54: Yes | F54: Retailer | G54: 275 | H54: Kg | I54: 275 | J54: 1 | K54: Kg | L54: 1
B55: M5-C-02 | C55: M5 | D55: S07 | E55: Yes | F55: Retailer | G55: 530 | H55: Kg | I55: 530 | J55: 2 | K55: Kg | L55: 2
B56: M5-C-03 | C56: M5 | D56: S05 | E56: Yes | F56: Retailer | G56: 620 | H56: Kg | I56: 620 | J56: 0.75 | K56: Kg | L56: 0.75
B57: M5-C-03 | C57: M5 | D57: S09 | E57: Yes | F57: Retailer | G57: 285 | H57: Kg | I57: 285 | J57: 3 | K57: Kg | L57: 3
B58: M5-C-03 | C58: M5 | D58: S04 | E58: No | G58: K
B59: M5-C-04 | C59: M5 | D59: S07 | E59: Yes | F59: Hawker | G59: 550 | H59: Kg | I59: 550 | J59: 0.5 | K59: Kg | L59: 0.5
B60: M5-C-04 | C60: M5 | D60: S05 | E60: No | G60: K
B61: M5-C-05 | C61: M5 | D61: S07 | E61: Yes | F61: Retailer | G61: 560 | H61: Kg | I61: 560 | J61: 0.5 | K61: Kg | L61: 0.5
B62: M5-C-05 | C62: M5 | D62: S09 | E62: Yes | F62: Retailer | G62: 275 | H62: Kg | I62: 275 | J62: 2 | K62: Kg | L62: 2
B63: M5-C-05 | C63: M5 | D63: S06 | E63: No | G63: K
B64: M6-C-01 | C64: M6 | D64: S09 | E64: Yes | F64: Retailer | G64: 265 | H64: Kg | I64: 265 | J64: 1.5 | K64: Kg | L64: 1.5
B65: M6-C-02 | C65: M6 | D65: S06 | E65: Yes | F65: Retailer | G65: 440 | H65: Kg | I65: 440 | J65: 1 | K65: Kg | L65: 1
B66: M6-C-02 | C66: M6 | D66: S09 | E66: Yes | F66: Retailer | G66: 260 | H66: Kg | I66: 260 | J66: 2.5 | K66: Kg | L66: 2.5
B67: M6-C-03 | C67: M6 | D67: S09 | E67: Yes | F67: Retailer | G67: 255 | H67: Kg | I67: 255 | J67: 1.5 | K67: Kg | L67: 1.5
B68: M6-C-04 | C68: M6 | D68: S01 | E68: Yes | F68: Retailer | G68: 1375 | H68: Kg | I68: 1375 | J68: 1.5 | K68: Kg | L68: 1.5
B69: M6-C-05 | C69: M6 | D69: S06 | E69: Yes | F69: Retailer | G69: 435 | H69: Kg | I69: 435 | J69: 0.75 | K69: Kg | L69: 0.75
B70: M6-C-05 | C70: M6 | D70: S01 | E70: No | G70: K

Sheet Consumer_Other_Fish
B2: Form C - Any Other Fish Bought (long format)
B4: Respondent_ID | C4: Market | D4: Fish_name_local | E4: Price_raw | F4: Unit | G4: Price_BDT_per_kg | H4: Quantity_raw | I4: Quantity_unit | J4: Quantity_kg | K4: Purchase_location | L4: Notes
B5: M1-C-01 | C5: M1 | D5: Chatka chingri | E5: 455 | F5: Kg | G5: 455 | H5: 0.75 | I5: Kg | J5: 0.75 | K5: Same market
B6: M1-C-01 | C6: M1 | D6: Datina | E6: 420 | F6: Kg | G6: 420 | H6: 1 | I6: Kg | J6: 1 | K6: Same market
B7: M1-C-04 | C7: M1 | D7: Bagda chingri | E7: 1130 | F7: Kg | G7: 1130 | H7: 0.5 | I7: Kg | J7: 0.5 | K7: Same market
B8: M1-C-04 | C8: M1 | D8: Kakra (crab) | E8: 585 | F8: Kg | G8: 585 | H8: 1 | I8: Kg | J8: 1 | K8: Same market
B9: M3-C-01 | C9: M3 | D9: Moid | E9: 155 | F9: Kg | G9: 155 | H9: 0.5 | I9: Kg | J9: 0.5 | K9: Neighbourhood van
B10: M3-C-03 | C10: M3 | D10: Datina | E10: 395 | F10: Kg | G10: 395 | H10: 1 | I10: Kg | J10: 1 | K10: Same market
B11: M3-C-03 | C11: M3 | D11: Moid | E11: 205 | F11: Kg | G11: 205 | H11: 0.5 | I11: Kg | J11: 0.5 | K11: Same market
B12: M3-C-04 | C12: M3 | D12: Datina | E12: 315 | F12: Kg | G12: 315 | H12: 0.5 | I12: Kg | J12: 0.5 | K12: Neighbourhood van
B13: M4-C-02 | C13: M4 | D13: Datina | E13: 370 | F13: Kg | G13: 370 | H13: 0.25 | I13: Kg | J13: 0.25 | K13: Same market
B14: M4-C-03 | C14: M4 | D14: Faisya | E14: 275 | F14: Kg | G14: 275 | H14: 0.25 | I14: Kg | J14: 0.25 | K14: Same market
B15: M4-C-03 | C15: M4 | D15: Khoira | E15: 345 | F15: Kg | G15: 345 | H15: 0.5 | I15: Kg | J15: 0.5 | K15: Neighbourhood van
B16: M5-C-03 | C16: M5 | D16: Lobster (local) | E16: 2340 | F16: Kg | G16: 2340 | H16: 0.75 | I16: Kg | J16: 0.75 | K16: Same market
... B24: M6-C-05 | C24: M6 | D24: Datina | E24: 340 | F24: Kg | G24: 340 | H24: 0.75 | I24: Kg | J24: 0.75 | K24: Neighbourhood van

Sheet Form_M_Market_Observation
B2: Form M - Market Observation Checklist (one row per market)
B4: Market | C4: Market_name | D4: Obs_Date | E4: Market_type | F4: Trading_hours | G4: Retail_stall_count | H4: Transport_access | I4: Platform_condition | J4: Roofing | K4: Drainage | L4: Electricity | M4: Ice_availability | N4: Ice_distance_note | O4: Sanitation | P4: Water_supply | Q4: Fee_arrangement | R4: Fee_rate_note | S4: GPS_coordinates | T4: Photo_references | U4: Evidence_source_note
B5: M1 | C5: Fishery Ghat | D5: 46084 | E5: Mixed | F5: 03:30-13:00 | G5: 210 | H5: Good | I5: Medium | J5: Partial | K5: Medium | L5: Irregular | M5: Available | N5: On-site ice factory, approx 150 m | O5: Poor | P5: Irregular | Q5: Aratdar | R5: 2.5-5% commission per lot; daily stall fee BDT 30-60 | S5: 22.3370, 91.8312 | T5: IMG_M1_01 to IMG_M1_04 | U5: Direct observation
B6: M2 | C6: Chawkbazar | D6: 46085 | E6: Retail | F6: 06:00-20:00 | G6: 160 | H6: Good | I6: Good | J6: Complete | K6: Medium | L6: Regular | M6: Available | N6: Two private ice suppliers at gate | O6: Medium | P6: Regular | Q6: Committee | R6: Daily toll BDT 50 per stall; monthly cleaning levy | S6: 22.3392, 91.8366 | T6: IMG_M2_01 to IMG_M2_04 | U6: Direct observation
B7: M3 | C7: Kazir Dewri | D7: 46086 | E7: Retail | F7: 06:30-19:30 | G7: 85 | H7: Medium | I7: Medium | J7: Partial | K7: Poor | L7: Regular | M7: Available | N7: Ice cart delivery from Bahaddarhat, 1.5 km | O7: Medium | P7: Regular | Q7: Committee | R7: Daily toll BDT 40 per stall | S7: 22.3415, 91.8301 | T7: IMG_M3_01 to IMG_M3_04 | U7: Direct observation
B8: M4 | C8: Karnaphuli Complex | D8: 46087 | E8: Retail | F8: 06:00-20:00 | G8: 120 | H8: Good | I8: Good | J8: Complete | K8: Good | L8: Regular | M8: Available | N8: Ice plant within market compound | O8: Good | P8: Regular | Q8: Committee | R8: Daily toll BDT 60; covered modern shed | S8: 22.3318, 91.8178 | T8: IMG_M4_01 to IMG_M4_04 | U8: Direct observation
B9: M5 | C9: Bahaddarhat | D9: 46088 | E9: Retail | F9: 06:30-20:00 | G9: 110 | H9: Medium | I9: Good | J9: Complete | K9: Medium | L9: Regular | M9: Available | N9: Adjacent ice factory, approx 300 m | O9: Medium | P9: Regular | Q9: Mixed | R9: Committee toll plus informal entry charge for vans | S9: 22.3611, 91.8230 | T9: IMG_M5_01 to IMG_M5_04 | U9: Direct observation
B10: M6 | C10: Patenga | D10: 46084 | E10: Mixed | F10: 04:00-12:30 | G10: 65 | H10: Medium | I10: Poor | J10: Partial | K10: Poor | L10: Irregular | M10: Available | N10: Private ice factory adjacent to landing | O10: Poor | P10: Irregular | Q10: Committee | R10: Landing-side fee per basket; BDT 20-40 per maund handled | S10: 22.2786, 91.7991 | T10: IMG_M6_01 to IMG_M6_04 | U10: Direct observation
B12: Twelve infrastructure items graded Good/Medium/Poor, Complete/Partial/None or Regular/Irregular/None as applicable (Methodology 3.5).

Sheet Tag_Price_Sheet
B2: Tag Price Sheet - displayed prices of all fish seen (optional, appendix only)
B4: Date | C4: Market | D4: Shop_or_Vendor_No | E4: Collector_initials | F4: Fish_name_local | G4: Price_raw | H4: Unit | I4: Price_BDT_per_kg | J4: Notes
B5: 46084 | C5: M1 | D5: V-01 | E5: RS | F5: Rupchanda | G5: 1470 | H5: Kg | I5: =IF(OR($G5="",$H5="",NOT(ISNUMBER($G5))),"",IF($H5="Maund",ROUND($G5/37.32,2),$G5))
B6: 46084 | C6: M1 | D6: V-01 | E6: RS | F6: Koral | G6: 825 | H6: Kg | I6: =IF(OR($G6="",$H6="",NOT(ISNUMBER($G6))),"",IF($H6="Maund",ROUND($G6/37.32,2),$G6))
B7: 46084 | C7: M1 | D7: V-01 | E7: RS | F7: Kakra (crab) | G7: 640 | H7: Kg | I7: =IF(OR($G7="",$H7="",NOT(ISNUMBER($G7))),"",IF($H7="Maund",ROUND($G7/37.32,2),$G7))
B8: 46084 | C8: M1 | D8: V-02 | E8: RS | F8: Poa | G8: 505 | H8: Kg | I8: =IF(OR($G8="",$H8="",NOT(ISNUMBER($G8))),"",IF($H8="Maund",ROUND($G8/37.32,2),$G8))
B9: 46084 | C9: M1 | D9: V-02 | E9: RS | F9: Kankoita | G9: 310 | H9: Kg | I9: =IF(OR($G9="",$H9="",NOT(ISNUMBER($G9))),"",IF($H9="Maund",ROUND($G9/37.32,2),$G9))
B10: 46084 | C10: M1 | D10: V-02 | E10: RS | F10: Khoira | G10: 245 | H10: Kg | I10: =IF(OR($G10="",$H10="",NOT(ISNUMBER($G10))),"",IF($H10="Maund",ROUND($G10/37.32,2),$G10))
B11: 46084 | C11: M1 | D11: V-03 | E11: RS | F11: Rupchanda | G11: 1445 | H11: Kg | I11: =IF(OR($G11="",$H11="",NOT(ISNUMBER($G11))),"",IF($H11="Maund",ROUND($G11/37.32,2),$G11))
B12: 46084 | C12: M1 | D12: V-03 | E12: RS | F12: Koral | G12: 835 | H12: Kg | I12: =IF(OR($G12="",$H12="",NOT(ISNUMBER($G12))),"",IF($H12="Maund",ROUND($G12/37.32,2),$G12))
B13: 46084 | C13: M1 | D13: V-04 | E13: RS | F13: Ilish | G13: 1315 | H13: Kg | I13: =IF(OR($G13="",$H13="",NOT(ISNUMBER($G13))),"",IF($H13="Maund",ROUND($G13/37.32,2),$G13))
B14: 46084 | C14: M1 | D14: V-04 | E14: RS | F14: Bagda chingri | G14: 810 | H14: Kg | I14: =IF(OR($G14="",$H14="",NOT(ISNUMBER($G14))),"",IF($H14="Maund",ROUND($G14/37.32,2),$G14))
B15: 46084 | C15: M1 | D15: V-05 | E15: RS | F15: Ilish | G15: 1315 | H15: Kg | I15: =IF(OR($G15="",$H15="",NOT(ISNUMBER($G15))),"",IF($H15="Maund",ROUND($G15/37.32,2),$G15))
B16: 46084 | C16: M1 | D16: V-05 | E16: RS | F16: Rupchanda | G16: 1440 | H16: Kg | I16: =IF(OR($G16="",$H16="",NOT(ISNUMBER($G16))),"",IF($H16="Maund",ROUND($G16/37.32,2),$G16))
... B140: 46084 | C140: M6 | D140: V-08 | E140: RS | F140: Poa | G140: 510 | H140: Kg | I140: =IF(OR($G140="",$H140="",NOT(ISNUMBER($G140))),"",IF($H140="Maund",ROUND($G140/37.32,2),$G140))
I141: =IF(OR($G141="",$H141="",NOT(ISNUMBER($G141))),"",IF($H141="Maund",ROUND($G141/37.32,2),$G141))
I142: =IF(OR($G142="",$H142="",NOT(ISNUMBER($G142))),"",IF($H142="Maund",ROUND($G142/37.32,2),$G142))
I143: =IF(OR($G143="",$H143="",NOT(ISNUMBER($G143))),"",IF($H143="Maund",ROUND($G143/37.32,2),$G143))
I144: =IF(OR($G144="",$H144="",NOT(ISNUMBER($G144))),"",IF($H144="Maund",ROUND($G144/37.32,2),$G144))
I145: =IF(OR($G145="",$H145="",NOT(ISNUMBER($G145))),"",IF($H145="Maund",ROUND($G145/37.32,2),$G145))
I146: =IF(OR($G146="",$H146="",NOT(ISNUMBER($G146))),"",IF($H146="Maund",ROUND($G146/37.32,2),$G146))
I147: =IF(OR($G147="",$H147="",NOT(ISNUMBER($G147))),"",IF($H147="Maund",ROUND($G147/37.32,2),$G147))
I148: =IF(OR($G148="",$H148="",NOT(ISNUMBER($G148))),"",IF($H148="Maund",ROUND($G148/37.32,2),$G148))
I149: =IF(OR($G149="",$H149="",NOT(ISNUMBER($G149))),"",IF($H149="Maund",ROUND($G149/37.32,2),$G149))
I150: =IF(OR($G150="",$H150="",NOT(ISNUMBER($G150))),"",IF($H150="Maund",ROUND($G150/37.32,2),$G150))
I151: =IF(OR($G151="",$H151="",NOT(ISNUMBER($G151))),"",IF($H151="Maund",ROUND($G151/37.32,2),$G151))
I152: =IF(OR($G152="",$H152="",NOT(ISNUMBER($G152))),"",IF($H152="Maund",ROUND($G152/37.32,2),$G152))
... I324: =IF(OR($G324="",$H324="",NOT(ISNUMBER($G324))),"",IF($H324="Maund",ROUND($G324/37.32,2),$G324))
B326: Spend ~10 minutes per arat listing every displayed price; never enters hypothesis tests, appendix descriptive table only.

Sheet QC_Check
B2: QC Check - automatic quality flags
B3: Everything on this sheet is formula-driven. Re-check after each entry session; fix the source sheet, never this one.
B5: Check | C5: Value | D5: Rule / target | E5: Status
B6: Form_A rows entered (Interview_Date filled) | C6: 30 | D6: 36 rows allocated (quota 30 + buffer 6) | E6: OK
B7: Form_B rows entered (Interview_Date filled) | C7: 30 | D7: 36 rows allocated (quota 30 + buffer 6) | E7: OK
B8: Form_R rows entered (Interview_Date filled) | C8: 30 | D8: 36 rows allocated (quota 30 + buffer 6) | E8: OK
B9: Form_C rows entered (Interview_Date filled) | C9: 30 | D9: 36 rows allocated (quota 30 + buffer 6) | E9: OK
B10: Total interviews entered | C10: 120 | D10: Field target 120 (Table 3.3) | E10: TARGET MET
B11: Duplicate Respondent_IDs - Form_A_Aratdar | C11: 0 | D11: 0 duplicates expected | E11: OK
B12: Duplicate Respondent_IDs - Form_B_Bepari_Faria | C12: 0 | D12: 0 duplicates expected | E12: OK
B13: Duplicate Respondent_IDs - Form_R_Khuchra | C13: 0 | D13: 0 duplicates expected | E13: OK
B14: Duplicate Respondent_IDs - Form_C_Consumer | C14: 0 | D14: 0 duplicates expected | E14: OK
B15: Payment % rows not summing to 100 - Form_A | C15: 0 | D15: Cash + MFS + Credit must equal 100 | E15: OK
B16: Payment % rows not summing to 100 - Form_B | C16: 0 | D16: Cash + MFS + Credit must equal 100 | E16: OK
B17: Payment % rows not summing to 100 - Form_R | C17: 0 | D17: Cash + MFS + Credit must equal 100 | E17: OK
... B29: Form_M completed (markets observed) | C29: 6 | D29: 6 markets | E29: COMPLETE
B31: Tip: use the filter arrows on each form sheet to find flagged rows (e.g. filter Respondent_ID, or sort by the offending column).
